{"version":3,"kind":"Article","sha256":"f7bca7ca40538502b7a107e68ebad30eab0b6a9712dedb1a01e5062fc4b9bd49","slug":"brainstorm-re-architecture","location":"/developer-guide/06-roadmap/brainstorm-re-architecture.md","dependencies":[],"frontmatter":{"title":"Rust Multi-Surface App Architecture Blueprint (v2)","date":"2026-02-21","label":"devflow.developer-guide.roadmap.brainstorm-re-architecture","authors":[{"nameParsed":{"literal":"Soft Mentor","given":"Soft","family":"Mentor"},"name":"Soft Mentor","id":"contributors-myst-generated-uid-0"}],"github":"https://github.com/softmentor/devflow","abbreviations":{"ADR":"Architecture Decision Record.","API":"Application Programming Interface.","CI":"Continuous Integration.","CLI":"Command Line Interface.","DAG":"Directed Acyclic Graph.","GHCR":"GitHub Container Registry.","PR":"Pull Request."},"numbering":{"title":{"offset":2}},"source_url":"https://github.com/softmentor/devflow/blob/main/docs/developer-guide/06-roadmap/brainstorm-re-architecture.md","edit_url":"https://github.com/softmentor/devflow/edit/main/docs/developer-guide/06-roadmap/brainstorm-re-architecture.md","exports":[{"format":"md","filename":"brainstorm-re-architecture.md","url":"/devflow/build/brainstorm-re-archit-b81bd411e8fcfd51da1f86ed45152bcf.md"}]},"mdast":{"type":"root","children":[{"type":"block","children":[{"type":"heading","depth":2,"position":{"start":{"line":7,"column":1},"end":{"line":7,"column":1}},"children":[{"type":"text","value":"1. Context","position":{"start":{"line":7,"column":1},"end":{"line":7,"column":1}},"key":"aSJOqhZoSQ"}],"identifier":"id-1-context","label":"1. Context","html_id":"id-1-context","implicit":true,"key":"OWGvfYmh5G"},{"type":"paragraph","position":{"start":{"line":9,"column":1},"end":{"line":9,"column":1}},"children":[{"type":"text","value":"This revision introduces a ","position":{"start":{"line":9,"column":1},"end":{"line":9,"column":1}},"key":"yrbzO83Upj"},{"type":"strong","position":{"start":{"line":9,"column":1},"end":{"line":9,"column":1}},"children":[{"type":"text","value":"first-class Interface & Communication Layer","position":{"start":{"line":9,"column":1},"end":{"line":9,"column":1}},"key":"Pk1mWEDtAQ"}],"key":"B8afqi4GS5"},{"type":"text","value":" that sits above the typed core and enables:","position":{"start":{"line":9,"column":1},"end":{"line":9,"column":1}},"key":"dqxlCmryYB"}],"key":"N3lIFkPoA1"},{"type":"list","ordered":false,"spread":false,"position":{"start":{"line":11,"column":1},"end":{"line":16,"column":1}},"children":[{"type":"listItem","spread":true,"position":{"start":{"line":11,"column":1},"end":{"line":11,"column":1}},"children":[{"type":"paragraph","children":[{"type":"text","value":"Transport abstraction (HTTP, RPC, Events, IPC)","position":{"start":{"line":11,"column":1},"end":{"line":11,"column":1}},"key":"VXhDkLphi6"}],"key":"AC5eOs3HxD"}],"key":"pqVNlU04T4"},{"type":"listItem","spread":true,"position":{"start":{"line":12,"column":1},"end":{"line":12,"column":1}},"children":[{"type":"paragraph","children":[{"type":"text","value":"Pluggable serialization formats","position":{"start":{"line":12,"column":1},"end":{"line":12,"column":1}},"key":"NceeCAbajB"}],"key":"pvA8Sohv2T"}],"key":"ansWPGweOE"},{"type":"listItem","spread":true,"position":{"start":{"line":13,"column":1},"end":{"line":13,"column":1}},"children":[{"type":"paragraph","children":[{"type":"text","value":"Zero-config sensible defaults","position":{"start":{"line":13,"column":1},"end":{"line":13,"column":1}},"key":"Nmsq7AyZaR"}],"key":"x9m2NkRyNh"}],"key":"boC1VMPTza"},{"type":"listItem","spread":true,"position":{"start":{"line":14,"column":1},"end":{"line":14,"column":1}},"children":[{"type":"paragraph","children":[{"type":"text","value":"Evolution without breaking adapters","position":{"start":{"line":14,"column":1},"end":{"line":14,"column":1}},"key":"uUmMrYeEqq"}],"key":"omeXuZmAAh"}],"key":"hqh6ILMidb"},{"type":"listItem","spread":true,"position":{"start":{"line":15,"column":1},"end":{"line":16,"column":1}},"children":[{"type":"paragraph","children":[{"type":"text","value":"Uniform debugging & observability","position":{"start":{"line":15,"column":1},"end":{"line":15,"column":1}},"key":"NxezaDtEuk"}],"key":"dW4UuRQmch"}],"key":"RHLUKhTuWp"}],"key":"e5E9lmc15U"},{"type":"paragraph","position":{"start":{"line":17,"column":1},"end":{"line":17,"column":1}},"children":[{"type":"text","value":"The goal is to preserve ","position":{"start":{"line":17,"column":1},"end":{"line":17,"column":1}},"key":"H2XmuhBcYK"},{"type":"strong","position":{"start":{"line":17,"column":1},"end":{"line":17,"column":1}},"children":[{"type":"text","value":"strong typing internally while allowing flexible external interfaces","position":{"start":{"line":17,"column":1},"end":{"line":17,"column":1}},"key":"Xx5WKfhm6W"}],"key":"kd7zLwzTR8"},{"type":"text","value":".","position":{"start":{"line":17,"column":1},"end":{"line":17,"column":1}},"key":"hKYhYnNq4l"}],"key":"kYIJlvTOF6"},{"type":"thematicBreak","position":{"start":{"line":19,"column":1},"end":{"line":19,"column":1}},"key":"aX9niD0x2n"},{"type":"heading","depth":2,"position":{"start":{"line":21,"column":1},"end":{"line":21,"column":1}},"children":[{"type":"text","value":"2. Updated High-Level Architecture","position":{"start":{"line":21,"column":1},"end":{"line":21,"column":1}},"key":"zaUvx8zNcp"}],"identifier":"id-2-updated-high-level-architecture","label":"2. Updated High-Level Architecture","html_id":"id-2-updated-high-level-architecture","implicit":true,"key":"aazH2Lm9rq"},{"type":"mermaid","value":"flowchart LR\n    core[Typed Core<br/>Domain + Services]\n    plugins[Plugins]\n    iface[Interface Layer<br/>Contracts + Payload + SerDe]\n    transport[Transport Layer]\n    adapters[Adapters]\n\n    core --> plugins\n    core --> iface\n    plugins --> iface\n    iface --> transport\n    transport --> adapters","position":{"start":{"line":23,"column":1},"end":{"line":36,"column":1}},"key":"ga7Uuksro6"},{"type":"heading","depth":4,"position":{"start":{"line":38,"column":1},"end":{"line":38,"column":1}},"children":[{"type":"text","value":"Key insight","position":{"start":{"line":38,"column":1},"end":{"line":38,"column":1}},"key":"yKIIJFS3wE"}],"identifier":"key-insight","label":"Key insight","html_id":"key-insight","implicit":true,"key":"Q3gy6IDNuQ"},{"type":"paragraph","position":{"start":{"line":39,"column":1},"end":{"line":40,"column":1}},"children":[{"type":"text","value":"Core does not depend on transport or serialization.","position":{"start":{"line":39,"column":1},"end":{"line":39,"column":1}},"key":"cjxJwqd4xu"},{"type":"break","position":{"start":{"line":39,"column":1},"end":{"line":39,"column":1}},"key":"B1MRhjJuBD"},{"type":"text","value":"Interfaces mediate between typed domain and external world.","position":{"start":{"line":39,"column":1},"end":{"line":39,"column":1}},"key":"NmYTUtnCGT"}],"key":"ltsDLGG8r0"},{"type":"thematicBreak","position":{"start":{"line":42,"column":1},"end":{"line":42,"column":1}},"key":"AHLq1nmEqe"},{"type":"heading","depth":2,"position":{"start":{"line":44,"column":1},"end":{"line":44,"column":1}},"children":[{"type":"text","value":"3. Interface Layer Responsibilities","position":{"start":{"line":44,"column":1},"end":{"line":44,"column":1}},"key":"uOyiYOCbeo"}],"identifier":"id-3-interface-layer-responsibilities","label":"3. Interface Layer Responsibilities","html_id":"id-3-interface-layer-responsibilities","implicit":true,"key":"MbozkuCeg1"},{"type":"heading","depth":3,"position":{"start":{"line":46,"column":1},"end":{"line":46,"column":1}},"children":[{"type":"text","value":"Responsibilities","position":{"start":{"line":46,"column":1},"end":{"line":46,"column":1}},"key":"RPnaeqxmeB"}],"identifier":"responsibilities","label":"Responsibilities","html_id":"responsibilities","implicit":true,"key":"Zc45AmJuoz"},{"type":"list","ordered":false,"spread":false,"position":{"start":{"line":47,"column":1},"end":{"line":53,"column":1}},"children":[{"type":"listItem","spread":true,"position":{"start":{"line":47,"column":1},"end":{"line":47,"column":1}},"children":[{"type":"paragraph","children":[{"type":"text","value":"Define contracts","position":{"start":{"line":47,"column":1},"end":{"line":47,"column":1}},"key":"hLL8OgLD0w"}],"key":"QUoBcusZ9p"}],"key":"cpUu9NOd8W"},{"type":"listItem","spread":true,"position":{"start":{"line":48,"column":1},"end":{"line":48,"column":1}},"children":[{"type":"paragraph","children":[{"type":"text","value":"Map domain ↔ payload","position":{"start":{"line":48,"column":1},"end":{"line":48,"column":1}},"key":"XFXtawEn8t"}],"key":"ljoREjS5nO"}],"key":"OdKBBqntSO"},{"type":"listItem","spread":true,"position":{"start":{"line":49,"column":1},"end":{"line":49,"column":1}},"children":[{"type":"paragraph","children":[{"type":"text","value":"Handle serialization formats","position":{"start":{"line":49,"column":1},"end":{"line":49,"column":1}},"key":"ccYHQNwh7r"}],"key":"EHPdMA1y9z"}],"key":"QgYzQ7Of0W"},{"type":"listItem","spread":true,"position":{"start":{"line":50,"column":1},"end":{"line":50,"column":1}},"children":[{"type":"paragraph","children":[{"type":"text","value":"Versioning","position":{"start":{"line":50,"column":1},"end":{"line":50,"column":1}},"key":"UnhIi5Uk1W"}],"key":"zfv13r6P9v"}],"key":"bJihTbf06g"},{"type":"listItem","spread":true,"position":{"start":{"line":51,"column":1},"end":{"line":51,"column":1}},"children":[{"type":"paragraph","children":[{"type":"text","value":"Validation","position":{"start":{"line":51,"column":1},"end":{"line":51,"column":1}},"key":"I2Ta2SBKHc"}],"key":"OlV5Pdhd6t"}],"key":"ffiaEtpTOY"},{"type":"listItem","spread":true,"position":{"start":{"line":52,"column":1},"end":{"line":53,"column":1}},"children":[{"type":"paragraph","children":[{"type":"text","value":"Error normalization","position":{"start":{"line":52,"column":1},"end":{"line":52,"column":1}},"key":"qpkKIHwRwd"}],"key":"YDkEf346FA"}],"key":"M5XUoKMIom"}],"key":"FOJeRWmlmW"},{"type":"thematicBreak","position":{"start":{"line":54,"column":1},"end":{"line":54,"column":1}},"key":"QKqQuan2r2"},{"type":"heading","depth":3,"position":{"start":{"line":56,"column":1},"end":{"line":56,"column":1}},"children":[{"type":"text","value":"Interface layer decomposition","position":{"start":{"line":56,"column":1},"end":{"line":56,"column":1}},"key":"lxmksVzlB6"}],"identifier":"interface-layer-decomposition","label":"Interface layer decomposition","html_id":"interface-layer-decomposition","implicit":true,"key":"TDdG0s0e0b"},{"type":"mermaid","value":"flowchart TD\n    contracts[Contracts<br/>Schema / WIT / OpenAPI]\n    mapping[Domain ↔ DTO Mapping]\n    payload[Payload Layer]\n    serde[SerDe Strategy]\n    versioning[Versioning]\n\n    contracts --> mapping\n    mapping --> payload\n    payload --> serde\n    contracts --> versioning","position":{"start":{"line":58,"column":1},"end":{"line":70,"column":1}},"key":"WiKaot9Rcq"},{"type":"thematicBreak","position":{"start":{"line":72,"column":1},"end":{"line":72,"column":1}},"key":"KsNIz9Ych6"},{"type":"heading","depth":2,"position":{"start":{"line":74,"column":1},"end":{"line":74,"column":1}},"children":[{"type":"text","value":"4. Transport Layer","position":{"start":{"line":74,"column":1},"end":{"line":74,"column":1}},"key":"pgFeRx2kbP"}],"identifier":"id-4-transport-layer","label":"4. Transport Layer","html_id":"id-4-transport-layer","implicit":true,"key":"DLNd8AS2pt"},{"type":"paragraph","position":{"start":{"line":76,"column":1},"end":{"line":76,"column":1}},"children":[{"type":"text","value":"Transport becomes a thin envelope around payload.","position":{"start":{"line":76,"column":1},"end":{"line":76,"column":1}},"key":"syUspc8thl"}],"key":"tGGiT0rFCo"},{"type":"mermaid","value":"flowchart TD\n    http[HTTP]\n    rpc[RPC]\n    events[Events]\n    ipc[IPC]\n    cli[CLI IO]\n\n    http --> payload[Payload]\n    rpc --> payload\n    events --> payload\n    ipc --> payload\n    cli --> payload","position":{"start":{"line":78,"column":1},"end":{"line":91,"column":1}},"key":"T2EbJseBcp"},{"type":"paragraph","position":{"start":{"line":93,"column":1},"end":{"line":93,"column":1}},"children":[{"type":"text","value":"This separation enables:","position":{"start":{"line":93,"column":1},"end":{"line":93,"column":1}},"key":"bCpbEl00X5"}],"key":"D3FdbiD1Zg"},{"type":"list","ordered":false,"spread":false,"position":{"start":{"line":95,"column":1},"end":{"line":98,"column":1}},"children":[{"type":"listItem","spread":true,"position":{"start":{"line":95,"column":1},"end":{"line":95,"column":1}},"children":[{"type":"paragraph","children":[{"type":"text","value":"Same payload across transports","position":{"start":{"line":95,"column":1},"end":{"line":95,"column":1}},"key":"U1qMCcxAPU"}],"key":"Z0Ibl3IimB"}],"key":"JrD4qJqe85"},{"type":"listItem","spread":true,"position":{"start":{"line":96,"column":1},"end":{"line":96,"column":1}},"children":[{"type":"paragraph","children":[{"type":"text","value":"Adapter portability","position":{"start":{"line":96,"column":1},"end":{"line":96,"column":1}},"key":"GUwSOa5N8T"}],"key":"sAjzsFipXq"}],"key":"BPD7CSRYVk"},{"type":"listItem","spread":true,"position":{"start":{"line":97,"column":1},"end":{"line":98,"column":1}},"children":[{"type":"paragraph","children":[{"type":"text","value":"Better testability","position":{"start":{"line":97,"column":1},"end":{"line":97,"column":1}},"key":"XBw0DsB9DL"}],"key":"uss0FDJ1va"}],"key":"aijxlMBpOB"}],"key":"ZaGrGczPlM"},{"type":"thematicBreak","position":{"start":{"line":99,"column":1},"end":{"line":99,"column":1}},"key":"xugrMqQwQp"},{"type":"heading","depth":2,"position":{"start":{"line":101,"column":1},"end":{"line":101,"column":1}},"children":[{"type":"text","value":"5. Payload Strategy","position":{"start":{"line":101,"column":1},"end":{"line":101,"column":1}},"key":"EB7fwseT5w"}],"identifier":"id-5-payload-strategy","label":"5. Payload Strategy","html_id":"id-5-payload-strategy","implicit":true,"key":"YeywIfs0Fi"},{"type":"heading","depth":3,"position":{"start":{"line":103,"column":1},"end":{"line":103,"column":1}},"children":[{"type":"text","value":"DTO layer (external representation)","position":{"start":{"line":103,"column":1},"end":{"line":103,"column":1}},"key":"vkbjlqE09y"}],"identifier":"dto-layer-external-representation","label":"DTO layer (external representation)","html_id":"dto-layer-external-representation","implicit":true,"key":"eP2KWjkzF1"},{"type":"list","ordered":false,"spread":false,"position":{"start":{"line":104,"column":1},"end":{"line":108,"column":1}},"children":[{"type":"listItem","spread":true,"position":{"start":{"line":104,"column":1},"end":{"line":104,"column":1}},"children":[{"type":"paragraph","children":[{"type":"text","value":"Immutable","position":{"start":{"line":104,"column":1},"end":{"line":104,"column":1}},"key":"NiAzm83ojg"}],"key":"Octne2TFdb"}],"key":"srxaVFk5BN"},{"type":"listItem","spread":true,"position":{"start":{"line":105,"column":1},"end":{"line":105,"column":1}},"children":[{"type":"paragraph","children":[{"type":"text","value":"Backward compatible","position":{"start":{"line":105,"column":1},"end":{"line":105,"column":1}},"key":"TI6DcSQ5hg"}],"key":"eTuAH7q0pc"}],"key":"N9dHH1PZL2"},{"type":"listItem","spread":true,"position":{"start":{"line":106,"column":1},"end":{"line":106,"column":1}},"children":[{"type":"paragraph","children":[{"type":"text","value":"Explicit versioning","position":{"start":{"line":106,"column":1},"end":{"line":106,"column":1}},"key":"GzWCV0NSKI"}],"key":"G98VcHKACa"}],"key":"doLL0nFJYd"},{"type":"listItem","spread":true,"position":{"start":{"line":107,"column":1},"end":{"line":108,"column":1}},"children":[{"type":"paragraph","children":[{"type":"text","value":"No domain invariants","position":{"start":{"line":107,"column":1},"end":{"line":107,"column":1}},"key":"Cn8Na7wbSF"}],"key":"v8ZCcRNK3z"}],"key":"wX5lHRtuaQ"}],"key":"CfDeQ6OpCy"},{"type":"heading","depth":3,"position":{"start":{"line":109,"column":1},"end":{"line":109,"column":1}},"children":[{"type":"text","value":"Mapping layer","position":{"start":{"line":109,"column":1},"end":{"line":109,"column":1}},"key":"b493zXsB9b"}],"identifier":"mapping-layer","label":"Mapping layer","html_id":"mapping-layer","implicit":true,"key":"c7sjwG6cg0"},{"type":"list","ordered":false,"spread":false,"position":{"start":{"line":110,"column":1},"end":{"line":112,"column":1}},"children":[{"type":"listItem","spread":true,"position":{"start":{"line":110,"column":1},"end":{"line":110,"column":1}},"children":[{"type":"paragraph","children":[{"type":"text","value":"Domain → DTO","position":{"start":{"line":110,"column":1},"end":{"line":110,"column":1}},"key":"UMU7iGtvzR"}],"key":"Oibtrk7SWV"}],"key":"NgK0Z6BWAA"},{"type":"listItem","spread":true,"position":{"start":{"line":111,"column":1},"end":{"line":112,"column":1}},"children":[{"type":"paragraph","children":[{"type":"text","value":"DTO → Domain (validation)","position":{"start":{"line":111,"column":1},"end":{"line":111,"column":1}},"key":"njFRfdyECO"}],"key":"oXcm64Ol0J"}],"key":"wu58vGHZ8C"}],"key":"Cfg0q8rdsb"},{"type":"thematicBreak","position":{"start":{"line":113,"column":1},"end":{"line":113,"column":1}},"key":"xUXrSNqdgC"},{"type":"heading","depth":2,"position":{"start":{"line":115,"column":1},"end":{"line":115,"column":1}},"children":[{"type":"text","value":"6. Serialization Strategy","position":{"start":{"line":115,"column":1},"end":{"line":115,"column":1}},"key":"LpGby69neV"}],"identifier":"id-6-serialization-strategy","label":"6. Serialization Strategy","html_id":"id-6-serialization-strategy","implicit":true,"key":"cjKIWXBtvN"},{"type":"heading","depth":3,"position":{"start":{"line":117,"column":1},"end":{"line":117,"column":1}},"children":[{"type":"text","value":"Requirements","position":{"start":{"line":117,"column":1},"end":{"line":117,"column":1}},"key":"JDmCQQplLh"}],"identifier":"requirements","label":"Requirements","html_id":"requirements","implicit":true,"key":"ToibJfNoZx"},{"type":"list","ordered":false,"spread":false,"position":{"start":{"line":118,"column":1},"end":{"line":122,"column":1}},"children":[{"type":"listItem","spread":true,"position":{"start":{"line":118,"column":1},"end":{"line":118,"column":1}},"children":[{"type":"paragraph","children":[{"type":"text","value":"Human friendly (debugging)","position":{"start":{"line":118,"column":1},"end":{"line":118,"column":1}},"key":"EzBwzIviJ6"}],"key":"SzTD2wnKLJ"}],"key":"SOCljcYnaG"},{"type":"listItem","spread":true,"position":{"start":{"line":119,"column":1},"end":{"line":119,"column":1}},"children":[{"type":"paragraph","children":[{"type":"text","value":"Efficient","position":{"start":{"line":119,"column":1},"end":{"line":119,"column":1}},"key":"Q4aJOOhSgL"}],"key":"buBRmzhefj"}],"key":"UAOVLYh4Tx"},{"type":"listItem","spread":true,"position":{"start":{"line":120,"column":1},"end":{"line":120,"column":1}},"children":[{"type":"paragraph","children":[{"type":"text","value":"Evolvable","position":{"start":{"line":120,"column":1},"end":{"line":120,"column":1}},"key":"cIPWEKUSUB"}],"key":"UE8Jt9IHys"}],"key":"C8kxHFyWH0"},{"type":"listItem","spread":true,"position":{"start":{"line":121,"column":1},"end":{"line":122,"column":1}},"children":[{"type":"paragraph","children":[{"type":"text","value":"Language neutral","position":{"start":{"line":121,"column":1},"end":{"line":121,"column":1}},"key":"DPx8U9YJ3V"}],"key":"cy2wk6Fw1c"}],"key":"F6xmggmHdu"}],"key":"xIPtBjYZuH"},{"type":"thematicBreak","position":{"start":{"line":123,"column":1},"end":{"line":123,"column":1}},"key":"wuBIbErtlY"},{"type":"heading","depth":3,"position":{"start":{"line":125,"column":1},"end":{"line":125,"column":1}},"children":[{"type":"text","value":"Multi-format SerDe model","position":{"start":{"line":125,"column":1},"end":{"line":125,"column":1}},"key":"lCH8eOoaxN"}],"identifier":"multi-format-serde-model","label":"Multi-format SerDe model","html_id":"multi-format-serde-model","implicit":true,"key":"nUp9M2z4fn"},{"type":"mermaid","value":"flowchart LR\n    dto[DTO Payload]\n    json[JSON]\n    cbor[CBOR]\n    msgpack[MsgPack]\n    proto[Protobuf]\n\n    dto --> json\n    dto --> cbor\n    dto --> msgpack\n    dto --> proto","position":{"start":{"line":127,"column":1},"end":{"line":139,"column":1}},"key":"AV6muF3VoE"},{"type":"thematicBreak","position":{"start":{"line":141,"column":1},"end":{"line":141,"column":1}},"key":"eM0NaNi5uT"},{"type":"heading","depth":3,"position":{"start":{"line":143,"column":1},"end":{"line":143,"column":1}},"children":[{"type":"text","value":"Recommended defaults","position":{"start":{"line":143,"column":1},"end":{"line":143,"column":1}},"key":"ngY6WJpmy8"}],"identifier":"recommended-defaults","label":"Recommended defaults","html_id":"recommended-defaults","implicit":true,"key":"gLH7aECS13"},{"type":"table","position":{"start":{"line":145,"column":1},"end":{"line":151,"column":1}},"children":[{"type":"tableRow","position":{"start":{"line":145,"column":1},"end":{"line":145,"column":1}},"children":[{"type":"tableCell","header":true,"position":{"start":{"line":145,"column":1},"end":{"line":145,"column":1}},"children":[{"type":"text","value":"Context","position":{"start":{"line":145,"column":1},"end":{"line":145,"column":1}},"key":"nswvTcvYmH"}],"key":"NRN7XXJ9ha"},{"type":"tableCell","header":true,"position":{"start":{"line":145,"column":1},"end":{"line":145,"column":1}},"children":[{"type":"text","value":"Format","position":{"start":{"line":145,"column":1},"end":{"line":145,"column":1}},"key":"nts9JjR4j6"}],"key":"Jvh7zXj18s"}],"key":"MKWnDlC2Ew"},{"type":"tableRow","position":{"start":{"line":147,"column":1},"end":{"line":147,"column":1}},"children":[{"type":"tableCell","position":{"start":{"line":147,"column":1},"end":{"line":147,"column":1}},"children":[{"type":"text","value":"Public ","key":"beoqz4a9gS"},{"type":"abbreviation","title":"Application Programming Interface.","children":[{"type":"text","value":"API","key":"vXcSpczjqk"}],"key":"F5ifIP9U9p"}],"key":"ap9rEobjAf"},{"type":"tableCell","position":{"start":{"line":147,"column":1},"end":{"line":147,"column":1}},"children":[{"type":"text","value":"JSON","position":{"start":{"line":147,"column":1},"end":{"line":147,"column":1}},"key":"OqPUl7h9V3"}],"key":"OOEET5Ro5N"}],"key":"yEmkiBNk78"},{"type":"tableRow","position":{"start":{"line":148,"column":1},"end":{"line":148,"column":1}},"children":[{"type":"tableCell","position":{"start":{"line":148,"column":1},"end":{"line":148,"column":1}},"children":[{"type":"text","value":"Internal RPC","position":{"start":{"line":148,"column":1},"end":{"line":148,"column":1}},"key":"Ldmk0I42Xu"}],"key":"bxGfLj8cyM"},{"type":"tableCell","position":{"start":{"line":148,"column":1},"end":{"line":148,"column":1}},"children":[{"type":"text","value":"MessagePack","position":{"start":{"line":148,"column":1},"end":{"line":148,"column":1}},"key":"hcLfnOb1eC"}],"key":"fyV6Htm6lN"}],"key":"AzEDeSvxPI"},{"type":"tableRow","position":{"start":{"line":149,"column":1},"end":{"line":149,"column":1}},"children":[{"type":"tableCell","position":{"start":{"line":149,"column":1},"end":{"line":149,"column":1}},"children":[{"type":"text","value":"Events","position":{"start":{"line":149,"column":1},"end":{"line":149,"column":1}},"key":"nvlmUMIIOR"}],"key":"qLYxI0H3Sb"},{"type":"tableCell","position":{"start":{"line":149,"column":1},"end":{"line":149,"column":1}},"children":[{"type":"text","value":"JSON / CloudEvents","position":{"start":{"line":149,"column":1},"end":{"line":149,"column":1}},"key":"tgP1FF3Mur"}],"key":"qB5e8cHwAw"}],"key":"qOD1ZSEspn"},{"type":"tableRow","position":{"start":{"line":150,"column":1},"end":{"line":150,"column":1}},"children":[{"type":"tableCell","position":{"start":{"line":150,"column":1},"end":{"line":150,"column":1}},"children":[{"type":"text","value":"WASM","position":{"start":{"line":150,"column":1},"end":{"line":150,"column":1}},"key":"MZke1ITPp5"}],"key":"GlBjIcVrL8"},{"type":"tableCell","position":{"start":{"line":150,"column":1},"end":{"line":150,"column":1}},"children":[{"type":"text","value":"WIT","position":{"start":{"line":150,"column":1},"end":{"line":150,"column":1}},"key":"tPtzCz2Vom"}],"key":"fxgoPO8DPZ"}],"key":"rk8684sUgP"},{"type":"tableRow","position":{"start":{"line":151,"column":1},"end":{"line":151,"column":1}},"children":[{"type":"tableCell","position":{"start":{"line":151,"column":1},"end":{"line":151,"column":1}},"children":[{"type":"text","value":"High throughput","position":{"start":{"line":151,"column":1},"end":{"line":151,"column":1}},"key":"ZnwuDBN6Y2"}],"key":"doPf02sYp1"},{"type":"tableCell","position":{"start":{"line":151,"column":1},"end":{"line":151,"column":1}},"children":[{"type":"text","value":"CBOR","position":{"start":{"line":151,"column":1},"end":{"line":151,"column":1}},"key":"qIhimNjTcs"}],"key":"Eo1fX2Ojq0"}],"key":"ho2RJspNia"}],"key":"yYcOx6utnl"},{"type":"thematicBreak","position":{"start":{"line":153,"column":1},"end":{"line":153,"column":1}},"key":"CV3cirsHRD"},{"type":"heading","depth":2,"position":{"start":{"line":155,"column":1},"end":{"line":155,"column":1}},"children":[{"type":"text","value":"7. Zero-Config Strategy","position":{"start":{"line":155,"column":1},"end":{"line":155,"column":1}},"key":"d3in7pZrKu"}],"identifier":"id-7-zero-config-strategy","label":"7. Zero-Config Strategy","html_id":"id-7-zero-config-strategy","implicit":true,"key":"WpR4GsxlO7"},{"type":"heading","depth":3,"position":{"start":{"line":157,"column":1},"end":{"line":157,"column":1}},"children":[{"type":"text","value":"Default path","position":{"start":{"line":157,"column":1},"end":{"line":157,"column":1}},"key":"eRrt3YWIf1"}],"identifier":"default-path","label":"Default path","html_id":"default-path","implicit":true,"key":"Wm7GmulI52"},{"type":"mermaid","value":"flowchart LR\n    core --> dto\n    dto --> json\n    json --> http","position":{"start":{"line":159,"column":1},"end":{"line":164,"column":1}},"key":"b3K2xMK5o4"},{"type":"paragraph","position":{"start":{"line":166,"column":1},"end":{"line":166,"column":1}},"children":[{"type":"text","value":"No configuration required for most users.","position":{"start":{"line":166,"column":1},"end":{"line":166,"column":1}},"key":"FVMJ5cMoCd"}],"key":"sfxT0WZ7rV"},{"type":"paragraph","position":{"start":{"line":168,"column":1},"end":{"line":168,"column":1}},"children":[{"type":"text","value":"Advanced users can override:","position":{"start":{"line":168,"column":1},"end":{"line":168,"column":1}},"key":"tIbxvet4F0"}],"key":"XU8q9BGrhI"},{"type":"list","ordered":false,"spread":false,"position":{"start":{"line":169,"column":1},"end":{"line":172,"column":1}},"children":[{"type":"listItem","spread":true,"position":{"start":{"line":169,"column":1},"end":{"line":169,"column":1}},"children":[{"type":"paragraph","children":[{"type":"text","value":"serialization format","position":{"start":{"line":169,"column":1},"end":{"line":169,"column":1}},"key":"kezegR1xxJ"}],"key":"s519olqRfi"}],"key":"CuN1qD8CBS"},{"type":"listItem","spread":true,"position":{"start":{"line":170,"column":1},"end":{"line":170,"column":1}},"children":[{"type":"paragraph","children":[{"type":"text","value":"transport","position":{"start":{"line":170,"column":1},"end":{"line":170,"column":1}},"key":"BUf87zLywK"}],"key":"GwtJUnn1ff"}],"key":"AHgzKkY1MD"},{"type":"listItem","spread":true,"position":{"start":{"line":171,"column":1},"end":{"line":172,"column":1}},"children":[{"type":"paragraph","children":[{"type":"text","value":"version negotiation","position":{"start":{"line":171,"column":1},"end":{"line":171,"column":1}},"key":"LwKmjB4248"}],"key":"q6IQkhMgMP"}],"key":"o3htQR6Ryv"}],"key":"mtZC0dbE3X"},{"type":"thematicBreak","position":{"start":{"line":173,"column":1},"end":{"line":173,"column":1}},"key":"xJCsIQGWtq"},{"type":"heading","depth":2,"position":{"start":{"line":175,"column":1},"end":{"line":175,"column":1}},"children":[{"type":"text","value":"8. Multi-Surface Interaction Flow","position":{"start":{"line":175,"column":1},"end":{"line":175,"column":1}},"key":"aaUjI20YE8"}],"identifier":"id-8-multi-surface-interaction-flow","label":"8. Multi-Surface Interaction Flow","html_id":"id-8-multi-surface-interaction-flow","implicit":true,"key":"iLSPerUt0z"},{"type":"mermaid","value":"sequenceDiagram\n    participant UI\n    participant Transport\n    participant Interface\n    participant Core\n    participant Plugins\n\n    UI->>Transport: Request\n    Transport->>Interface: Envelope\n    Interface->>Core: Typed input\n    Core->>Plugins: Execute\n    Plugins-->>Core: Result\n    Core-->>Interface: Typed output\n    Interface-->>Transport: Serialized payload\n    Transport-->>UI: Response","position":{"start":{"line":177,"column":1},"end":{"line":193,"column":1}},"key":"XRuE5f173b"},{"type":"thematicBreak","position":{"start":{"line":195,"column":1},"end":{"line":195,"column":1}},"key":"jtHZLk6Yeo"},{"type":"heading","depth":2,"position":{"start":{"line":197,"column":1},"end":{"line":197,"column":1}},"children":[{"type":"text","value":"9. Risk Mitigation Strategies","position":{"start":{"line":197,"column":1},"end":{"line":197,"column":1}},"key":"tLaz6arARc"}],"identifier":"id-9-risk-mitigation-strategies","label":"9. Risk Mitigation Strategies","html_id":"id-9-risk-mitigation-strategies","implicit":true,"key":"simpF5AleX"},{"type":"heading","depth":3,"position":{"start":{"line":199,"column":1},"end":{"line":199,"column":1}},"children":[{"type":"text","value":"Risk 1 — Version drift across repos","position":{"start":{"line":199,"column":1},"end":{"line":199,"column":1}},"key":"dcm5ePaxZu"}],"identifier":"risk-1-version-drift-across-repos","label":"Risk 1 — Version drift across repos","html_id":"risk-1-version-drift-across-repos","implicit":true,"key":"QRBJucpHHS"},{"type":"heading","depth":4,"position":{"start":{"line":201,"column":1},"end":{"line":201,"column":1}},"children":[{"type":"text","value":"Mitigation","position":{"start":{"line":201,"column":1},"end":{"line":201,"column":1}},"key":"PnyRO7Nuvu"}],"identifier":"mitigation","label":"Mitigation","html_id":"mitigation","implicit":true,"key":"ECNfLtMGn5"},{"type":"list","ordered":false,"spread":false,"position":{"start":{"line":202,"column":1},"end":{"line":206,"column":1}},"children":[{"type":"listItem","spread":true,"position":{"start":{"line":202,"column":1},"end":{"line":202,"column":1}},"children":[{"type":"paragraph","children":[{"type":"text","value":"Contract-first design","position":{"start":{"line":202,"column":1},"end":{"line":202,"column":1}},"key":"gtHICkLQMB"}],"key":"at7bHieRsC"}],"key":"vbftkC02MO"},{"type":"listItem","spread":true,"position":{"start":{"line":203,"column":1},"end":{"line":203,"column":1}},"children":[{"type":"paragraph","children":[{"type":"text","value":"Schema version pinning","position":{"start":{"line":203,"column":1},"end":{"line":203,"column":1}},"key":"E6N3XRzVPo"}],"key":"FMJUkrLHe4"}],"key":"vlBmZxqDqe"},{"type":"listItem","spread":true,"position":{"start":{"line":204,"column":1},"end":{"line":204,"column":1}},"children":[{"type":"paragraph","children":[{"type":"text","value":"Compatibility test suite","position":{"start":{"line":204,"column":1},"end":{"line":204,"column":1}},"key":"r3bxIbW9he"}],"key":"N0nVEmHe4H"}],"key":"UehrS8AVEb"},{"type":"listItem","spread":true,"position":{"start":{"line":205,"column":1},"end":{"line":206,"column":1}},"children":[{"type":"paragraph","children":[{"type":"text","value":"Interface conformance tests","position":{"start":{"line":205,"column":1},"end":{"line":205,"column":1}},"key":"zLjQw6RA39"}],"key":"Q5KKNujF1O"}],"key":"r3oiRnJ4Kv"}],"key":"PYWaWs7WBD"},{"type":"thematicBreak","position":{"start":{"line":207,"column":1},"end":{"line":207,"column":1}},"key":"Ohtkld8ykv"},{"type":"heading","depth":3,"position":{"start":{"line":209,"column":1},"end":{"line":209,"column":1}},"children":[{"type":"text","value":"Risk 2 — Serialization overhead","position":{"start":{"line":209,"column":1},"end":{"line":209,"column":1}},"key":"t1gb42SYa5"}],"identifier":"risk-2-serialization-overhead","label":"Risk 2 — Serialization overhead","html_id":"risk-2-serialization-overhead","implicit":true,"key":"rTA31dGF8l"},{"type":"heading","depth":4,"position":{"start":{"line":211,"column":1},"end":{"line":211,"column":1}},"children":[{"type":"text","value":"Mitigation","position":{"start":{"line":211,"column":1},"end":{"line":211,"column":1}},"key":"BdxFwFbI21"}],"identifier":"mitigation","label":"Mitigation","html_id":"mitigation-1","implicit":true,"key":"LiThfQgdp3"},{"type":"list","ordered":false,"spread":false,"position":{"start":{"line":212,"column":1},"end":{"line":216,"column":1}},"children":[{"type":"listItem","spread":true,"position":{"start":{"line":212,"column":1},"end":{"line":212,"column":1}},"children":[{"type":"paragraph","children":[{"type":"text","value":"Binary formats for internal paths","position":{"start":{"line":212,"column":1},"end":{"line":212,"column":1}},"key":"uTBXTm7jwb"}],"key":"u5xEk9e8ot"}],"key":"FViXEgkIPj"},{"type":"listItem","spread":true,"position":{"start":{"line":213,"column":1},"end":{"line":213,"column":1}},"children":[{"type":"paragraph","children":[{"type":"text","value":"Zero-copy deserialization where possible","position":{"start":{"line":213,"column":1},"end":{"line":213,"column":1}},"key":"wXDN9RdUEJ"}],"key":"Pu8hRoDpM7"}],"key":"VwwQVq153Z"},{"type":"listItem","spread":true,"position":{"start":{"line":214,"column":1},"end":{"line":214,"column":1}},"children":[{"type":"paragraph","children":[{"type":"text","value":"DTO flattening","position":{"start":{"line":214,"column":1},"end":{"line":214,"column":1}},"key":"npPOGzNbRt"}],"key":"qPAc35vVjB"}],"key":"TZDYdwaRGq"},{"type":"listItem","spread":true,"position":{"start":{"line":215,"column":1},"end":{"line":216,"column":1}},"children":[{"type":"paragraph","children":[{"type":"text","value":"Avoid domain → DTO churn","position":{"start":{"line":215,"column":1},"end":{"line":215,"column":1}},"key":"cfXHnq72td"}],"key":"arJbDaVBVa"}],"key":"P8autKEwnh"}],"key":"r2wdw5QVRv"},{"type":"thematicBreak","position":{"start":{"line":217,"column":1},"end":{"line":217,"column":1}},"key":"tKBCTvCYFW"},{"type":"heading","depth":3,"position":{"start":{"line":219,"column":1},"end":{"line":219,"column":1}},"children":[{"type":"text","value":"Risk 3 — Plugin ABI instability","position":{"start":{"line":219,"column":1},"end":{"line":219,"column":1}},"key":"ec3RLQdOFB"}],"identifier":"risk-3-plugin-abi-instability","label":"Risk 3 — Plugin ABI instability","html_id":"risk-3-plugin-abi-instability","implicit":true,"key":"R3gfueiEeN"},{"type":"heading","depth":4,"position":{"start":{"line":221,"column":1},"end":{"line":221,"column":1}},"children":[{"type":"text","value":"Mitigation","position":{"start":{"line":221,"column":1},"end":{"line":221,"column":1}},"key":"PRnZq0wQ6u"}],"identifier":"mitigation","label":"Mitigation","html_id":"mitigation-2","implicit":true,"key":"LyuuJKzIHg"},{"type":"list","ordered":false,"spread":false,"position":{"start":{"line":222,"column":1},"end":{"line":226,"column":1}},"children":[{"type":"listItem","spread":true,"position":{"start":{"line":222,"column":1},"end":{"line":222,"column":1}},"children":[{"type":"paragraph","children":[{"type":"text","value":"WASM plugin boundary","position":{"start":{"line":222,"column":1},"end":{"line":222,"column":1}},"key":"JMffIayo70"}],"key":"E0HtPtlO6r"}],"key":"zbMjpkWcOc"},{"type":"listItem","spread":true,"position":{"start":{"line":223,"column":1},"end":{"line":223,"column":1}},"children":[{"type":"paragraph","children":[{"type":"text","value":"Stable plugin ","key":"xBcQ2h0Co3"},{"type":"abbreviation","title":"Application Programming Interface.","children":[{"type":"text","value":"API","key":"FNOzxyaKwp"}],"key":"dyoeMpYOxE"},{"type":"text","value":" crate","key":"tfagWDAAkN"}],"key":"zpBoK9yWIa"}],"key":"y1rB3ZXIYw"},{"type":"listItem","spread":true,"position":{"start":{"line":224,"column":1},"end":{"line":224,"column":1}},"children":[{"type":"paragraph","children":[{"type":"text","value":"Capability-based interfaces","position":{"start":{"line":224,"column":1},"end":{"line":224,"column":1}},"key":"avbAzmPLsf"}],"key":"YoQeUCozB8"}],"key":"k72ToyMDMf"},{"type":"listItem","spread":true,"position":{"start":{"line":225,"column":1},"end":{"line":226,"column":1}},"children":[{"type":"paragraph","children":[{"type":"text","value":"Version handshake","position":{"start":{"line":225,"column":1},"end":{"line":225,"column":1}},"key":"YYcDkNnK71"}],"key":"a7DYlQlqw6"}],"key":"lGK3JX5wSK"}],"key":"dhxDPqxrvt"},{"type":"thematicBreak","position":{"start":{"line":227,"column":1},"end":{"line":227,"column":1}},"key":"eCHeyPXZp9"},{"type":"heading","depth":3,"position":{"start":{"line":229,"column":1},"end":{"line":229,"column":1}},"children":[{"type":"text","value":"Risk 4 — Integration complexity","position":{"start":{"line":229,"column":1},"end":{"line":229,"column":1}},"key":"kMAjsZoG1I"}],"identifier":"risk-4-integration-complexity","label":"Risk 4 — Integration complexity","html_id":"risk-4-integration-complexity","implicit":true,"key":"pOfqlsUq5X"},{"type":"heading","depth":4,"position":{"start":{"line":231,"column":1},"end":{"line":231,"column":1}},"children":[{"type":"text","value":"Mitigation","position":{"start":{"line":231,"column":1},"end":{"line":231,"column":1}},"key":"qQiRtrarvC"}],"identifier":"mitigation","label":"Mitigation","html_id":"mitigation-3","implicit":true,"key":"PVm1x7eGeg"},{"type":"list","ordered":false,"spread":false,"position":{"start":{"line":232,"column":1},"end":{"line":236,"column":1}},"children":[{"type":"listItem","spread":true,"position":{"start":{"line":232,"column":1},"end":{"line":232,"column":1}},"children":[{"type":"paragraph","children":[{"type":"text","value":"Meta integration repo","position":{"start":{"line":232,"column":1},"end":{"line":232,"column":1}},"key":"RLmqFkTHoS"}],"key":"nbSeMrecwF"}],"key":"ghPNDboF1J"},{"type":"listItem","spread":true,"position":{"start":{"line":233,"column":1},"end":{"line":233,"column":1}},"children":[{"type":"paragraph","children":[{"type":"text","value":"Contract mocks","position":{"start":{"line":233,"column":1},"end":{"line":233,"column":1}},"key":"n9zvLZqLkv"}],"key":"IimZOgXOGa"}],"key":"JUf3mMIkfu"},{"type":"listItem","spread":true,"position":{"start":{"line":234,"column":1},"end":{"line":234,"column":1}},"children":[{"type":"paragraph","children":[{"type":"text","value":"Adapter test harness","position":{"start":{"line":234,"column":1},"end":{"line":234,"column":1}},"key":"S9d4uy7R4K"}],"key":"tUENjnkeGZ"}],"key":"mbT0z6VdZU"},{"type":"listItem","spread":true,"position":{"start":{"line":235,"column":1},"end":{"line":236,"column":1}},"children":[{"type":"paragraph","children":[{"type":"text","value":"Devcontainer for reproducibility","position":{"start":{"line":235,"column":1},"end":{"line":235,"column":1}},"key":"wVqXTzaJco"}],"key":"dTmN80VmUl"}],"key":"tXXYl9ko67"}],"key":"UjkXo8sk0a"},{"type":"thematicBreak","position":{"start":{"line":237,"column":1},"end":{"line":237,"column":1}},"key":"oJjWfFEY5r"},{"type":"heading","depth":3,"position":{"start":{"line":239,"column":1},"end":{"line":239,"column":1}},"children":[{"type":"text","value":"Risk 5 — Debuggability loss with binary formats","position":{"start":{"line":239,"column":1},"end":{"line":239,"column":1}},"key":"EEucd3hYK6"}],"identifier":"risk-5-debuggability-loss-with-binary-formats","label":"Risk 5 — Debuggability loss with binary formats","html_id":"risk-5-debuggability-loss-with-binary-formats","implicit":true,"key":"oKNpd6FwnJ"},{"type":"heading","depth":4,"position":{"start":{"line":241,"column":1},"end":{"line":241,"column":1}},"children":[{"type":"text","value":"Mitigation","position":{"start":{"line":241,"column":1},"end":{"line":241,"column":1}},"key":"fkoXHmPEOn"}],"identifier":"mitigation","label":"Mitigation","html_id":"mitigation-4","implicit":true,"key":"j8pTrde0vo"},{"type":"list","ordered":false,"spread":false,"position":{"start":{"line":242,"column":1},"end":{"line":245,"column":1}},"children":[{"type":"listItem","spread":true,"position":{"start":{"line":242,"column":1},"end":{"line":242,"column":1}},"children":[{"type":"paragraph","children":[{"type":"text","value":"Debug mode JSON mirror","position":{"start":{"line":242,"column":1},"end":{"line":242,"column":1}},"key":"ytdnWbUppy"}],"key":"uZTxPUhq1n"}],"key":"T4kEAiBzdz"},{"type":"listItem","spread":true,"position":{"start":{"line":243,"column":1},"end":{"line":243,"column":1}},"children":[{"type":"paragraph","children":[{"type":"text","value":"Structured tracing payload logs","position":{"start":{"line":243,"column":1},"end":{"line":243,"column":1}},"key":"guw26TUrdR"}],"key":"fVLXfUKGqD"}],"key":"WfjMSfC4Ar"},{"type":"listItem","spread":true,"position":{"start":{"line":244,"column":1},"end":{"line":245,"column":1}},"children":[{"type":"paragraph","children":[{"type":"text","value":"Schema-aware inspector tools","position":{"start":{"line":244,"column":1},"end":{"line":244,"column":1}},"key":"KaXU3G0q4c"}],"key":"WkJFGeAUSp"}],"key":"KUUAfNACZ1"}],"key":"VPAu2Ei3rB"},{"type":"thematicBreak","position":{"start":{"line":246,"column":1},"end":{"line":246,"column":1}},"key":"aUQLTsDQZf"},{"type":"heading","depth":2,"position":{"start":{"line":248,"column":1},"end":{"line":248,"column":1}},"children":[{"type":"text","value":"10. Evolution Strategy","position":{"start":{"line":248,"column":1},"end":{"line":248,"column":1}},"key":"oWLVVk22Nt"}],"identifier":"id-10-evolution-strategy","label":"10. Evolution Strategy","html_id":"id-10-evolution-strategy","implicit":true,"key":"AuME9xwYoC"},{"type":"heading","depth":3,"position":{"start":{"line":250,"column":1},"end":{"line":250,"column":1}},"children":[{"type":"text","value":"Layered evolution model","position":{"start":{"line":250,"column":1},"end":{"line":250,"column":1}},"key":"d8fUJ35XBw"}],"identifier":"layered-evolution-model","label":"Layered evolution model","html_id":"layered-evolution-model","implicit":true,"key":"T0X8jL08Nu"},{"type":"mermaid","value":"flowchart TD\n    domain[Domain]\n    contracts[Contracts]\n    payload[Payload]\n    serde[SerDe]\n    transport[Transport]\n\n    domain --> contracts\n    contracts --> payload\n    payload --> serde\n    serde --> transport","position":{"start":{"line":252,"column":1},"end":{"line":264,"column":1}},"key":"FiSHIv3kHc"},{"type":"heading","depth":4,"position":{"start":{"line":266,"column":1},"end":{"line":266,"column":1}},"children":[{"type":"text","value":"Principle","position":{"start":{"line":266,"column":1},"end":{"line":266,"column":1}},"key":"aOLfmrg8hk"}],"identifier":"principle","label":"Principle","html_id":"principle","implicit":true,"key":"uNBReMXwRX"},{"type":"paragraph","position":{"start":{"line":267,"column":1},"end":{"line":267,"column":1}},"children":[{"type":"text","value":"Each layer evolves independently with compatibility guarantees.","position":{"start":{"line":267,"column":1},"end":{"line":267,"column":1}},"key":"txS7Puvf2p"}],"key":"C5lS3VjD4O"},{"type":"thematicBreak","position":{"start":{"line":269,"column":1},"end":{"line":269,"column":1}},"key":"PJG5NL9C02"},{"type":"heading","depth":2,"position":{"start":{"line":271,"column":1},"end":{"line":271,"column":1}},"children":[{"type":"text","value":"11. Contract Strategy","position":{"start":{"line":271,"column":1},"end":{"line":271,"column":1}},"key":"XSM59w8bdp"}],"identifier":"id-11-contract-strategy","label":"11. Contract Strategy","html_id":"id-11-contract-strategy","implicit":true,"key":"LC664pBbj7"},{"type":"heading","depth":3,"position":{"start":{"line":273,"column":1},"end":{"line":273,"column":1}},"children":[{"type":"text","value":"Contract sources","position":{"start":{"line":273,"column":1},"end":{"line":273,"column":1}},"key":"KLDWQimIyD"}],"identifier":"contract-sources","label":"Contract sources","html_id":"contract-sources","implicit":true,"key":"PIJ9QEEPT2"},{"type":"list","ordered":false,"spread":false,"position":{"start":{"line":274,"column":1},"end":{"line":278,"column":1}},"children":[{"type":"listItem","spread":true,"position":{"start":{"line":274,"column":1},"end":{"line":274,"column":1}},"children":[{"type":"paragraph","children":[{"type":"text","value":"Open","key":"afntZ44rxH"},{"type":"abbreviation","title":"Application Programming Interface.","children":[{"type":"text","value":"API","key":"rcUfVSvrp1"}],"key":"XCDZvZL6SJ"},{"type":"text","value":" (HTTP)","key":"N7BFXUIbyO"}],"key":"rHL1OMaO5r"}],"key":"XZIf81yn8A"},{"type":"listItem","spread":true,"position":{"start":{"line":275,"column":1},"end":{"line":275,"column":1}},"children":[{"type":"paragraph","children":[{"type":"text","value":"JSON Schema (DTO)","position":{"start":{"line":275,"column":1},"end":{"line":275,"column":1}},"key":"XvaDvd8klW"}],"key":"WlroUyB8YD"}],"key":"E9zBYHr5HQ"},{"type":"listItem","spread":true,"position":{"start":{"line":276,"column":1},"end":{"line":276,"column":1}},"children":[{"type":"paragraph","children":[{"type":"text","value":"WIT (WASM)","position":{"start":{"line":276,"column":1},"end":{"line":276,"column":1}},"key":"DHFv3wA2gx"}],"key":"o2yEqo0vyI"}],"key":"CTJIoJuNKS"},{"type":"listItem","spread":true,"position":{"start":{"line":277,"column":1},"end":{"line":278,"column":1}},"children":[{"type":"paragraph","children":[{"type":"text","value":"Protobuf (optional internal)","position":{"start":{"line":277,"column":1},"end":{"line":277,"column":1}},"key":"TYDtOXLkN8"}],"key":"UVIOVHTnyB"}],"key":"pXNhlEZRgC"}],"key":"LM9syG0U3V"},{"type":"thematicBreak","position":{"start":{"line":279,"column":1},"end":{"line":279,"column":1}},"key":"kbSX3tHxYc"},{"type":"heading","depth":3,"position":{"start":{"line":281,"column":1},"end":{"line":281,"column":1}},"children":[{"type":"text","value":"Contract sharing","position":{"start":{"line":281,"column":1},"end":{"line":281,"column":1}},"key":"K3plCnRxPz"}],"identifier":"contract-sharing","label":"Contract sharing","html_id":"contract-sharing","implicit":true,"key":"MC1nvZTGJ2"},{"type":"mermaid","value":"flowchart LR\n    schema[Schema Source]\n    rust[Rust Types]\n    ts[TS Types]\n    docs[Docs]\n\n    schema --> rust\n    schema --> ts\n    schema --> docs","position":{"start":{"line":283,"column":1},"end":{"line":293,"column":1}},"key":"suW07WCOGg"},{"type":"thematicBreak","position":{"start":{"line":295,"column":1},"end":{"line":295,"column":1}},"key":"f6kpy7Wgfh"},{"type":"heading","depth":2,"position":{"start":{"line":297,"column":1},"end":{"line":297,"column":1}},"children":[{"type":"text","value":"12. Error Handling Model","position":{"start":{"line":297,"column":1},"end":{"line":297,"column":1}},"key":"q77WYqyUeo"}],"identifier":"id-12-error-handling-model","label":"12. Error Handling Model","html_id":"id-12-error-handling-model","implicit":true,"key":"DkTHmNBp7h"},{"type":"heading","depth":3,"position":{"start":{"line":299,"column":1},"end":{"line":299,"column":1}},"children":[{"type":"text","value":"Unified error envelope","position":{"start":{"line":299,"column":1},"end":{"line":299,"column":1}},"key":"jjh6iwni1i"}],"identifier":"unified-error-envelope","label":"Unified error envelope","html_id":"unified-error-envelope","implicit":true,"key":"MQnb3QuQMS"},{"type":"code","lang":"json","value":"{\n  \"type\": \"https://example/errors/invalid-input\",\n  \"title\": \"Invalid input\",\n  \"detail\": \"...\",\n  \"trace_id\": \"...\",\n  \"instance\": \"...\",\n  \"metadata\": {}\n}","position":{"start":{"line":301,"column":1},"end":{"line":310,"column":1}},"key":"QTa8XwKszp"},{"type":"paragraph","position":{"start":{"line":312,"column":1},"end":{"line":312,"column":1}},"children":[{"type":"text","value":"Based on RFC7807.","position":{"start":{"line":312,"column":1},"end":{"line":312,"column":1}},"key":"hph57ILwBx"}],"key":"zDREp1neQ0"},{"type":"thematicBreak","position":{"start":{"line":314,"column":1},"end":{"line":314,"column":1}},"key":"qszb9aIRQ6"},{"type":"heading","depth":2,"position":{"start":{"line":316,"column":1},"end":{"line":316,"column":1}},"children":[{"type":"text","value":"13. Security Strategy","position":{"start":{"line":316,"column":1},"end":{"line":316,"column":1}},"key":"qVKYenwjkk"}],"identifier":"id-13-security-strategy","label":"13. Security Strategy","html_id":"id-13-security-strategy","implicit":true,"key":"vupDVsgj6s"},{"type":"list","ordered":false,"spread":false,"position":{"start":{"line":318,"column":1},"end":{"line":325,"column":1}},"children":[{"type":"listItem","spread":true,"position":{"start":{"line":318,"column":1},"end":{"line":318,"column":1}},"children":[{"type":"paragraph","children":[{"type":"text","value":"Capability-based plugin permissions","position":{"start":{"line":318,"column":1},"end":{"line":318,"column":1}},"key":"yhJcdk4QBy"}],"key":"wMgxhVSGCo"}],"key":"fuZtNLhRF0"},{"type":"listItem","spread":true,"position":{"start":{"line":319,"column":1},"end":{"line":319,"column":1}},"children":[{"type":"paragraph","children":[{"type":"text","value":"Signed plugin manifests","position":{"start":{"line":319,"column":1},"end":{"line":319,"column":1}},"key":"UY10Mh5Eyl"}],"key":"cGYIDHbuzi"}],"key":"KatYIRVriW"},{"type":"listItem","spread":true,"position":{"start":{"line":320,"column":1},"end":{"line":320,"column":1}},"children":[{"type":"paragraph","children":[{"type":"text","value":"Schema validation","position":{"start":{"line":320,"column":1},"end":{"line":320,"column":1}},"key":"MoHdlRD9eG"}],"key":"xAzijmPslN"}],"key":"FKJ2jDyDH1"},{"type":"listItem","spread":true,"position":{"start":{"line":321,"column":1},"end":{"line":321,"column":1}},"children":[{"type":"paragraph","children":[{"type":"text","value":"Input sanitization","position":{"start":{"line":321,"column":1},"end":{"line":321,"column":1}},"key":"wNH5A5IKRM"}],"key":"aFUrz0B9RO"}],"key":"YbseQAwrrm"},{"type":"listItem","spread":true,"position":{"start":{"line":322,"column":1},"end":{"line":322,"column":1}},"children":[{"type":"paragraph","children":[{"type":"text","value":"Event provenance","position":{"start":{"line":322,"column":1},"end":{"line":322,"column":1}},"key":"Uf6iln17zd"}],"key":"iSdb9KWGZl"}],"key":"f7AOXh3fuW"},{"type":"listItem","spread":true,"position":{"start":{"line":323,"column":1},"end":{"line":323,"column":1}},"children":[{"type":"paragraph","children":[{"type":"text","value":"Content Security Policy (webviews)","position":{"start":{"line":323,"column":1},"end":{"line":323,"column":1}},"key":"nHBbuxVLbI"}],"key":"GAK0nG11AS"}],"key":"LUonbzka7F"},{"type":"listItem","spread":true,"position":{"start":{"line":324,"column":1},"end":{"line":325,"column":1}},"children":[{"type":"paragraph","children":[{"type":"text","value":"Transport encryption","position":{"start":{"line":324,"column":1},"end":{"line":324,"column":1}},"key":"PVYmoGQRss"}],"key":"OfNc5e4sS9"}],"key":"OeXVlUl60Y"}],"key":"q8b8h2s3mc"},{"type":"thematicBreak","position":{"start":{"line":326,"column":1},"end":{"line":326,"column":1}},"key":"jo334sm9sG"},{"type":"heading","depth":2,"position":{"start":{"line":328,"column":1},"end":{"line":328,"column":1}},"children":[{"type":"text","value":"14. Trade-off Summary","position":{"start":{"line":328,"column":1},"end":{"line":328,"column":1}},"key":"ryrvZnuadt"}],"identifier":"id-14-trade-off-summary","label":"14. Trade-off Summary","html_id":"id-14-trade-off-summary","implicit":true,"key":"hWVfw2p6SD"},{"type":"table","position":{"start":{"line":330,"column":1},"end":{"line":336,"column":1}},"children":[{"type":"tableRow","position":{"start":{"line":330,"column":1},"end":{"line":330,"column":1}},"children":[{"type":"tableCell","header":true,"position":{"start":{"line":330,"column":1},"end":{"line":330,"column":1}},"children":[{"type":"text","value":"Decision","position":{"start":{"line":330,"column":1},"end":{"line":330,"column":1}},"key":"gMFiorYqg7"}],"key":"ZrbKmS7BFl"},{"type":"tableCell","header":true,"position":{"start":{"line":330,"column":1},"end":{"line":330,"column":1}},"children":[{"type":"text","value":"Benefit","position":{"start":{"line":330,"column":1},"end":{"line":330,"column":1}},"key":"wBhpVs09Lv"}],"key":"II6mYhpCP5"},{"type":"tableCell","header":true,"position":{"start":{"line":330,"column":1},"end":{"line":330,"column":1}},"children":[{"type":"text","value":"Cost","position":{"start":{"line":330,"column":1},"end":{"line":330,"column":1}},"key":"gZgWmNwuAA"}],"key":"AG0OE2aJrv"}],"key":"n8PLlmduKo"},{"type":"tableRow","position":{"start":{"line":332,"column":1},"end":{"line":332,"column":1}},"children":[{"type":"tableCell","position":{"start":{"line":332,"column":1},"end":{"line":332,"column":1}},"children":[{"type":"text","value":"Separate transport & payload","position":{"start":{"line":332,"column":1},"end":{"line":332,"column":1}},"key":"G0IKgPdKhb"}],"key":"FXbVOFBSbU"},{"type":"tableCell","position":{"start":{"line":332,"column":1},"end":{"line":332,"column":1}},"children":[{"type":"text","value":"Flexibility","position":{"start":{"line":332,"column":1},"end":{"line":332,"column":1}},"key":"zVPw0dCvf8"}],"key":"xF6ESQyuH2"},{"type":"tableCell","position":{"start":{"line":332,"column":1},"end":{"line":332,"column":1}},"children":[{"type":"text","value":"Complexity","position":{"start":{"line":332,"column":1},"end":{"line":332,"column":1}},"key":"f72apY8a72"}],"key":"rgIixW3A7r"}],"key":"p06U8HVmW9"},{"type":"tableRow","position":{"start":{"line":333,"column":1},"end":{"line":333,"column":1}},"children":[{"type":"tableCell","position":{"start":{"line":333,"column":1},"end":{"line":333,"column":1}},"children":[{"type":"text","value":"Interface layer","position":{"start":{"line":333,"column":1},"end":{"line":333,"column":1}},"key":"S3RKZpquMO"}],"key":"UXRvlN0f14"},{"type":"tableCell","position":{"start":{"line":333,"column":1},"end":{"line":333,"column":1}},"children":[{"type":"text","value":"Evolution safety","position":{"start":{"line":333,"column":1},"end":{"line":333,"column":1}},"key":"WVxrDrbXEk"}],"key":"QqfRoy6uzz"},{"type":"tableCell","position":{"start":{"line":333,"column":1},"end":{"line":333,"column":1}},"children":[{"type":"text","value":"Extra mapping","position":{"start":{"line":333,"column":1},"end":{"line":333,"column":1}},"key":"kVkLhvNWaQ"}],"key":"PLciTxN7QH"}],"key":"pYY2SSXmGX"},{"type":"tableRow","position":{"start":{"line":334,"column":1},"end":{"line":334,"column":1}},"children":[{"type":"tableCell","position":{"start":{"line":334,"column":1},"end":{"line":334,"column":1}},"children":[{"type":"text","value":"Multi-format SerDe","position":{"start":{"line":334,"column":1},"end":{"line":334,"column":1}},"key":"l0PO8p7ISa"}],"key":"u36RxWPFwk"},{"type":"tableCell","position":{"start":{"line":334,"column":1},"end":{"line":334,"column":1}},"children":[{"type":"text","value":"Performance","position":{"start":{"line":334,"column":1},"end":{"line":334,"column":1}},"key":"t4m3GN46Sb"}],"key":"F8K2x5tCBD"},{"type":"tableCell","position":{"start":{"line":334,"column":1},"end":{"line":334,"column":1}},"children":[{"type":"text","value":"Tooling overhead","position":{"start":{"line":334,"column":1},"end":{"line":334,"column":1}},"key":"w0rxffH2Xs"}],"key":"wyQ0Nl7ceZ"}],"key":"b8E7tcLJu0"},{"type":"tableRow","position":{"start":{"line":335,"column":1},"end":{"line":335,"column":1}},"children":[{"type":"tableCell","position":{"start":{"line":335,"column":1},"end":{"line":335,"column":1}},"children":[{"type":"text","value":"Contract-first design","position":{"start":{"line":335,"column":1},"end":{"line":335,"column":1}},"key":"cMie2194LD"}],"key":"T90YZj59eC"},{"type":"tableCell","position":{"start":{"line":335,"column":1},"end":{"line":335,"column":1}},"children":[{"type":"text","value":"Stability","position":{"start":{"line":335,"column":1},"end":{"line":335,"column":1}},"key":"YbkneUHJqq"}],"key":"fSztSZPQN4"},{"type":"tableCell","position":{"start":{"line":335,"column":1},"end":{"line":335,"column":1}},"children":[{"type":"text","value":"Slower iteration","position":{"start":{"line":335,"column":1},"end":{"line":335,"column":1}},"key":"xr6NurXDX9"}],"key":"IrOxlBC6fu"}],"key":"MjJeUStsFu"},{"type":"tableRow","position":{"start":{"line":336,"column":1},"end":{"line":336,"column":1}},"children":[{"type":"tableCell","position":{"start":{"line":336,"column":1},"end":{"line":336,"column":1}},"children":[{"type":"text","value":"WASM plugins","position":{"start":{"line":336,"column":1},"end":{"line":336,"column":1}},"key":"eUwgHQqvwy"}],"key":"C0oAiUO1eJ"},{"type":"tableCell","position":{"start":{"line":336,"column":1},"end":{"line":336,"column":1}},"children":[{"type":"text","value":"Safety","position":{"start":{"line":336,"column":1},"end":{"line":336,"column":1}},"key":"OJ1Jvbmeps"}],"key":"Hqfb09scYG"},{"type":"tableCell","position":{"start":{"line":336,"column":1},"end":{"line":336,"column":1}},"children":[{"type":"text","value":"Runtime overhead","position":{"start":{"line":336,"column":1},"end":{"line":336,"column":1}},"key":"iVQAm5iA2S"}],"key":"JmZRtvAjXN"}],"key":"m30eshQPnQ"}],"key":"AOkD6u0qWr"},{"type":"thematicBreak","position":{"start":{"line":338,"column":1},"end":{"line":338,"column":1}},"key":"WfvIJKY67W"},{"type":"heading","depth":2,"position":{"start":{"line":340,"column":1},"end":{"line":340,"column":1}},"children":[{"type":"text","value":"15. Final Opinionated Model","position":{"start":{"line":340,"column":1},"end":{"line":340,"column":1}},"key":"MGCXBHyzoi"}],"identifier":"id-15-final-opinionated-model","label":"15. Final Opinionated Model","html_id":"id-15-final-opinionated-model","implicit":true,"key":"lln2ek3EhX"},{"type":"table","position":{"start":{"line":342,"column":1},"end":{"line":350,"column":1}},"children":[{"type":"tableRow","position":{"start":{"line":342,"column":1},"end":{"line":342,"column":1}},"children":[{"type":"tableCell","header":true,"position":{"start":{"line":342,"column":1},"end":{"line":342,"column":1}},"children":[{"type":"text","value":"Layer","position":{"start":{"line":342,"column":1},"end":{"line":342,"column":1}},"key":"e7zsEyg4bi"}],"key":"V6kNe0PzG3"},{"type":"tableCell","header":true,"position":{"start":{"line":342,"column":1},"end":{"line":342,"column":1}},"children":[{"type":"text","value":"Responsibility","position":{"start":{"line":342,"column":1},"end":{"line":342,"column":1}},"key":"pmywBRR9EB"}],"key":"GRV7uB24yj"}],"key":"AmBsdsHIzz"},{"type":"tableRow","position":{"start":{"line":344,"column":1},"end":{"line":344,"column":1}},"children":[{"type":"tableCell","position":{"start":{"line":344,"column":1},"end":{"line":344,"column":1}},"children":[{"type":"text","value":"Core","position":{"start":{"line":344,"column":1},"end":{"line":344,"column":1}},"key":"umUwguTqs0"}],"key":"MJDmrCp745"},{"type":"tableCell","position":{"start":{"line":344,"column":1},"end":{"line":344,"column":1}},"children":[{"type":"text","value":"Domain + workflows","position":{"start":{"line":344,"column":1},"end":{"line":344,"column":1}},"key":"dFtQjbIKmY"}],"key":"PS9Pk1ontw"}],"key":"uYEd5nZWAE"},{"type":"tableRow","position":{"start":{"line":345,"column":1},"end":{"line":345,"column":1}},"children":[{"type":"tableCell","position":{"start":{"line":345,"column":1},"end":{"line":345,"column":1}},"children":[{"type":"text","value":"Plugins","position":{"start":{"line":345,"column":1},"end":{"line":345,"column":1}},"key":"UTB2pYGUZM"}],"key":"kKW2G9LH4z"},{"type":"tableCell","position":{"start":{"line":345,"column":1},"end":{"line":345,"column":1}},"children":[{"type":"text","value":"Capability extension","position":{"start":{"line":345,"column":1},"end":{"line":345,"column":1}},"key":"D4pc9AeHXr"}],"key":"Cqz8riel3a"}],"key":"OtnEk2lQmM"},{"type":"tableRow","position":{"start":{"line":346,"column":1},"end":{"line":346,"column":1}},"children":[{"type":"tableCell","position":{"start":{"line":346,"column":1},"end":{"line":346,"column":1}},"children":[{"type":"text","value":"Interface","position":{"start":{"line":346,"column":1},"end":{"line":346,"column":1}},"key":"hYSQ77uFxi"}],"key":"UX5CfImAsJ"},{"type":"tableCell","position":{"start":{"line":346,"column":1},"end":{"line":346,"column":1}},"children":[{"type":"text","value":"Contracts + mapping","position":{"start":{"line":346,"column":1},"end":{"line":346,"column":1}},"key":"v2Z5omwXNC"}],"key":"Lc311ylyJf"}],"key":"dUSE7xXCXz"},{"type":"tableRow","position":{"start":{"line":347,"column":1},"end":{"line":347,"column":1}},"children":[{"type":"tableCell","position":{"start":{"line":347,"column":1},"end":{"line":347,"column":1}},"children":[{"type":"text","value":"Payload","position":{"start":{"line":347,"column":1},"end":{"line":347,"column":1}},"key":"kYyKeh6XdZ"}],"key":"kuoRoKlP6t"},{"type":"tableCell","position":{"start":{"line":347,"column":1},"end":{"line":347,"column":1}},"children":[{"type":"text","value":"DTO","position":{"start":{"line":347,"column":1},"end":{"line":347,"column":1}},"key":"ARyTzPoS6z"}],"key":"UpGN89Tx7j"}],"key":"Lk3QKLaZ3B"},{"type":"tableRow","position":{"start":{"line":348,"column":1},"end":{"line":348,"column":1}},"children":[{"type":"tableCell","position":{"start":{"line":348,"column":1},"end":{"line":348,"column":1}},"children":[{"type":"text","value":"SerDe","position":{"start":{"line":348,"column":1},"end":{"line":348,"column":1}},"key":"E1lff9Ueea"}],"key":"HM5qoAkvbq"},{"type":"tableCell","position":{"start":{"line":348,"column":1},"end":{"line":348,"column":1}},"children":[{"type":"text","value":"Encoding","position":{"start":{"line":348,"column":1},"end":{"line":348,"column":1}},"key":"tx4N93fMBu"}],"key":"zncgJKntnM"}],"key":"OoltqntAI3"},{"type":"tableRow","position":{"start":{"line":349,"column":1},"end":{"line":349,"column":1}},"children":[{"type":"tableCell","position":{"start":{"line":349,"column":1},"end":{"line":349,"column":1}},"children":[{"type":"text","value":"Transport","position":{"start":{"line":349,"column":1},"end":{"line":349,"column":1}},"key":"DHuZTkHHZb"}],"key":"CyzF647n7V"},{"type":"tableCell","position":{"start":{"line":349,"column":1},"end":{"line":349,"column":1}},"children":[{"type":"text","value":"Delivery","position":{"start":{"line":349,"column":1},"end":{"line":349,"column":1}},"key":"aUL3oFmf2I"}],"key":"hFyvl1CsWL"}],"key":"ZhmL83uwWO"},{"type":"tableRow","position":{"start":{"line":350,"column":1},"end":{"line":350,"column":1}},"children":[{"type":"tableCell","position":{"start":{"line":350,"column":1},"end":{"line":350,"column":1}},"children":[{"type":"text","value":"Adapters","position":{"start":{"line":350,"column":1},"end":{"line":350,"column":1}},"key":"kenVtjDnhQ"}],"key":"cRtgqm3BFy"},{"type":"tableCell","position":{"start":{"line":350,"column":1},"end":{"line":350,"column":1}},"children":[{"type":"text","value":"Surface integration","position":{"start":{"line":350,"column":1},"end":{"line":350,"column":1}},"key":"mmKFrsaD7S"}],"key":"xTNBWFV2OB"}],"key":"Cx4Jr1kRSB"}],"key":"XVXQGXM7E6"},{"type":"thematicBreak","position":{"start":{"line":352,"column":1},"end":{"line":352,"column":1}},"key":"YB3pQQcY8H"},{"type":"heading","depth":2,"position":{"start":{"line":354,"column":1},"end":{"line":354,"column":1}},"children":[{"type":"text","value":"16. Future Evolution Opportunities","position":{"start":{"line":354,"column":1},"end":{"line":354,"column":1}},"key":"pAAQyMOBID"}],"identifier":"id-16-future-evolution-opportunities","label":"16. Future Evolution Opportunities","html_id":"id-16-future-evolution-opportunities","implicit":true,"key":"tGC8bQWI10"},{"type":"list","ordered":false,"spread":false,"position":{"start":{"line":356,"column":1},"end":{"line":363,"column":1}},"children":[{"type":"listItem","spread":true,"position":{"start":{"line":356,"column":1},"end":{"line":356,"column":1}},"children":[{"type":"paragraph","children":[{"type":"text","value":"Agent-native interfaces","position":{"start":{"line":356,"column":1},"end":{"line":356,"column":1}},"key":"R5XG0aIF2Z"}],"key":"bE5gzG8ooC"}],"key":"pL6vRDKnHS"},{"type":"listItem","spread":true,"position":{"start":{"line":357,"column":1},"end":{"line":357,"column":1}},"children":[{"type":"paragraph","children":[{"type":"text","value":"Graph-based contracts","position":{"start":{"line":357,"column":1},"end":{"line":357,"column":1}},"key":"k7g9sDgmvs"}],"key":"JkfZLd9nBz"}],"key":"ocmx0ixLEt"},{"type":"listItem","spread":true,"position":{"start":{"line":358,"column":1},"end":{"line":358,"column":1}},"children":[{"type":"paragraph","children":[{"type":"text","value":"Schema registry","position":{"start":{"line":358,"column":1},"end":{"line":358,"column":1}},"key":"gbZCiDNOO1"}],"key":"dL4OKYkLD3"}],"key":"nenZJwSsrC"},{"type":"listItem","spread":true,"position":{"start":{"line":359,"column":1},"end":{"line":359,"column":1}},"children":[{"type":"paragraph","children":[{"type":"text","value":"Event mesh","position":{"start":{"line":359,"column":1},"end":{"line":359,"column":1}},"key":"ShQDSWD2Sd"}],"key":"PlqyRgzasl"}],"key":"TAfvKYIXyY"},{"type":"listItem","spread":true,"position":{"start":{"line":360,"column":1},"end":{"line":360,"column":1}},"children":[{"type":"paragraph","children":[{"type":"text","value":"Edge adapter layer","position":{"start":{"line":360,"column":1},"end":{"line":360,"column":1}},"key":"pXyGk56AJ5"}],"key":"LWkM1ZNMaD"}],"key":"mLzFeLaN1Q"},{"type":"listItem","spread":true,"position":{"start":{"line":361,"column":1},"end":{"line":361,"column":1}},"children":[{"type":"paragraph","children":[{"type":"text","value":"Semantic version negotiation","position":{"start":{"line":361,"column":1},"end":{"line":361,"column":1}},"key":"K3gjFaVG0R"}],"key":"aLkJjZ95EY"}],"key":"H9ivQv4KP4"},{"type":"listItem","spread":true,"position":{"start":{"line":362,"column":1},"end":{"line":363,"column":1}},"children":[{"type":"paragraph","children":[{"type":"text","value":"Self-describing plugins","position":{"start":{"line":362,"column":1},"end":{"line":362,"column":1}},"key":"XLGDQSJRtz"}],"key":"QMtXQYPoFz"}],"key":"IsiaOitdAq"}],"key":"iJSZigU7mU"},{"type":"thematicBreak","position":{"start":{"line":364,"column":1},"end":{"line":364,"column":1}},"key":"wLogHWlqZU"},{"type":"heading","depth":2,"position":{"start":{"line":366,"column":1},"end":{"line":366,"column":1}},"children":[{"type":"text","value":"17. Next Possible Deep Dives","position":{"start":{"line":366,"column":1},"end":{"line":366,"column":1}},"key":"QzKI4WhHbz"}],"identifier":"id-17-next-possible-deep-dives","label":"17. Next Possible Deep Dives","html_id":"id-17-next-possible-deep-dives","implicit":true,"key":"okz4LIjSbc"},{"type":"list","ordered":false,"spread":false,"position":{"start":{"line":368,"column":1},"end":{"line":374,"column":1}},"children":[{"type":"listItem","spread":true,"position":{"start":{"line":368,"column":1},"end":{"line":368,"column":1}},"children":[{"type":"paragraph","children":[{"type":"text","value":"DTO mapping patterns (Rust)","position":{"start":{"line":368,"column":1},"end":{"line":368,"column":1}},"key":"mM1PXZvWNS"}],"key":"FgMX4sskmw"}],"key":"yw8bQEUdNf"},{"type":"listItem","spread":true,"position":{"start":{"line":369,"column":1},"end":{"line":369,"column":1}},"children":[{"type":"paragraph","children":[{"type":"text","value":"WIT contract examples","position":{"start":{"line":369,"column":1},"end":{"line":369,"column":1}},"key":"nudOubd2Af"}],"key":"R1Lb3icdFS"}],"key":"f05anbNW0A"},{"type":"listItem","spread":true,"position":{"start":{"line":370,"column":1},"end":{"line":370,"column":1}},"children":[{"type":"paragraph","children":[{"type":"text","value":"Plugin runtime protocol","position":{"start":{"line":370,"column":1},"end":{"line":370,"column":1}},"key":"bisjwWbSES"}],"key":"JzAflyZB3S"}],"key":"groPl7o40u"},{"type":"listItem","spread":true,"position":{"start":{"line":371,"column":1},"end":{"line":371,"column":1}},"children":[{"type":"paragraph","children":[{"type":"text","value":"Schema evolution patterns","position":{"start":{"line":371,"column":1},"end":{"line":371,"column":1}},"key":"LftVT8On7C"}],"key":"ljJ0iXRk5w"}],"key":"ajb8sL9yVc"},{"type":"listItem","spread":true,"position":{"start":{"line":372,"column":1},"end":{"line":372,"column":1}},"children":[{"type":"paragraph","children":[{"type":"text","value":"Adapter test harness design","position":{"start":{"line":372,"column":1},"end":{"line":372,"column":1}},"key":"SSumOJOI2Y"}],"key":"hejiNQaMVH"}],"key":"vXwLcNfHZC"},{"type":"listItem","spread":true,"position":{"start":{"line":373,"column":1},"end":{"line":373,"column":1}},"children":[{"type":"paragraph","children":[{"type":"text","value":"Multi-repo ","key":"dMCo4UE4Y1"},{"type":"abbreviation","title":"Continuous Integration.","children":[{"type":"text","value":"CI","key":"SsuJMpgUUL"}],"key":"x9F5Isyt1W"},{"type":"text","value":" orchestration","key":"BfoSRu5PXZ"}],"key":"u2DpW8cXmJ"}],"key":"uzf6qq49mb"},{"type":"listItem","spread":true,"position":{"start":{"line":374,"column":1},"end":{"line":374,"column":1}},"children":[{"type":"paragraph","children":[{"type":"text","value":"Contract compatibility checker","position":{"start":{"line":374,"column":1},"end":{"line":374,"column":1}},"key":"KS9pNPJuQY"}],"key":"VVqeUP4CZB"}],"key":"H3DzFyv5yJ"}],"key":"eyeaUF1NJJ"}],"key":"de4LWxHb7Q"}],"key":"AdOYeLjMHy"},"references":{"cite":{"order":[],"data":{}}},"footer":{"navigation":{"prev":{"title":"Rust Multi-Surface Architecture — Implementation Blueprint","url":"/brainstorm-implementation","group":"06 Roadmap"},"next":{"title":"References","url":"/references","group":"07 Resources"}}},"domain":"http://localhost:3000"}