{"version":3,"kind":"Article","sha256":"bd02a43daee41218111ed34f429843ab3b184feb9dcf054ab50c91074f5857eb","slug":"index","location":"/index.md","dependencies":[],"frontmatter":{"title":"Devflow - Deterministic Developer Workflows","label":"devflow.index","site":{"hide_toc":true,"hide_outline":true,"hide_title_block":true},"authors":[{"nameParsed":{"literal":"Soft Mentor","given":"Soft","family":"Mentor"},"name":"Soft Mentor","id":"contributors-myst-generated-uid-0"}],"github":"https://github.com/softmentor/devflow","abbreviations":{"ADR":"Architecture Decision Record.","API":"Application Programming Interface.","CI":"Continuous Integration.","CLI":"Command Line Interface.","DAG":"Directed Acyclic Graph.","GHCR":"GitHub Container Registry.","PR":"Pull Request."},"source_url":"https://github.com/softmentor/devflow/blob/main/docs/index.md","edit_url":"https://github.com/softmentor/devflow/edit/main/docs/index.md","thumbnail":"/devflow/build/devflow-landing-c6e725077d09f0b6661bb5b3045c9aa4.svg","exports":[{"format":"md","filename":"index.md","url":"/devflow/build/index-53eacf966fce3eda639f164aaf92ae9c.md"}]},"mdast":{"type":"root","children":[{"type":"block","position":{"start":{"line":10,"column":1},"end":{"line":10,"column":1}},"children":[{"type":"paragraph","position":{"start":{"line":12,"column":1},"end":{"line":12,"column":1}},"children":[{"type":"text","value":"Deterministic Workflows","position":{"start":{"line":12,"column":1},"end":{"line":12,"column":1}},"key":"tPcxEnjh0h"}],"key":"zfurAFLXwL"},{"type":"heading","depth":2,"position":{"start":{"line":14,"column":1},"end":{"line":14,"column":1}},"children":[{"type":"text","value":"One Command Surface","position":{"start":{"line":14,"column":1},"end":{"line":14,"column":1}},"key":"RZlUVV2MDl"}],"identifier":"one-command-surface","label":"One Command Surface","html_id":"one-command-surface","implicit":true,"key":"XmG4UgWWvJ"},{"type":"heading","depth":2,"position":{"start":{"line":15,"column":1},"end":{"line":15,"column":1}},"children":[{"type":"text","value":"Local and ","key":"bC2XDSWHBG"},{"type":"abbreviation","title":"Continuous Integration.","children":[{"type":"text","value":"CI","key":"I0Vwq64drM"}],"key":"znBTsjPe6c"},{"type":"text","value":" Parity","key":"DkzIaw47MM"}],"identifier":"local-and-ci-parity","label":"Local and CI Parity","html_id":"local-and-ci-parity","implicit":true,"key":"WjTwupo6TC"},{"type":"paragraph","position":{"start":{"line":17,"column":1},"end":{"line":17,"column":1}},"children":[{"type":"text","value":"Devflow provides stable commands and profile-driven orchestration for building, testing, and validating software across stacks.","position":{"start":{"line":17,"column":1},"end":{"line":17,"column":1}},"key":"I5vxdvjLvw"}],"key":"dS6Kh4CEZv"},{"type":"image","url":"/devflow/build/devflow-landing-c6e725077d09f0b6661bb5b3045c9aa4.svg","align":"center","class":"only-light","key":"cgYLQqg6lQ","urlSource":"assets/images/devflow-landing.svg"},{"type":"image","url":"/devflow/build/devflow-landing-c6e725077d09f0b6661bb5b3045c9aa4.svg","align":"center","class":"only-dark","key":"vahiY3KNv2","urlSource":"assets/images/devflow-landing.svg"},{"type":"paragraph","position":{"start":{"line":26,"column":1},"end":{"line":26,"column":1}},"children":[{"type":"link","children":[{"type":"text","value":"Get Started","key":"Co6S5pxap3"}],"class":"button","identifier":"devflow.user-guide.getting-started","label":"devflow.user-guide.getting-started","url":"/getting-started","internal":true,"dataUrl":"/getting-started.json","key":"syWs2xJdjV"}],"key":"P6ac169dm1"}],"kind":"split-image","key":"RLZqFB5kUi"},{"type":"block","position":{"start":{"line":28,"column":1},"end":{"line":28,"column":1}},"children":[{"type":"heading","depth":3,"position":{"start":{"line":30,"column":1},"end":{"line":30,"column":1}},"children":[{"type":"text","value":"What Devflow Solves","position":{"start":{"line":30,"column":1},"end":{"line":30,"column":1}},"key":"y2wwIPD6BB"}],"identifier":"what-devflow-solves","label":"What Devflow Solves","html_id":"what-devflow-solves","implicit":true,"key":"IbzXqgHLsZ"},{"type":"list","ordered":false,"spread":false,"position":{"start":{"line":32,"column":1},"end":{"line":35,"column":1}},"children":[{"type":"listItem","spread":true,"position":{"start":{"line":32,"column":1},"end":{"line":32,"column":1}},"children":[{"type":"paragraph","children":[{"type":"text","value":"Consistent command contract (","position":{"start":{"line":32,"column":1},"end":{"line":32,"column":1}},"key":"BYFNktQgWV"},{"type":"inlineCode","value":"setup","position":{"start":{"line":32,"column":1},"end":{"line":32,"column":1}},"key":"rg2XsjlO5w"},{"type":"text","value":", ","position":{"start":{"line":32,"column":1},"end":{"line":32,"column":1}},"key":"bNyo2MkkR6"},{"type":"inlineCode","value":"fmt","position":{"start":{"line":32,"column":1},"end":{"line":32,"column":1}},"key":"lhXhE3omVA"},{"type":"text","value":", ","position":{"start":{"line":32,"column":1},"end":{"line":32,"column":1}},"key":"BrMBZsoNLr"},{"type":"inlineCode","value":"lint","position":{"start":{"line":32,"column":1},"end":{"line":32,"column":1}},"key":"ETR3Yi5V8X"},{"type":"text","value":", ","position":{"start":{"line":32,"column":1},"end":{"line":32,"column":1}},"key":"Jvhdf8c1WZ"},{"type":"inlineCode","value":"build","position":{"start":{"line":32,"column":1},"end":{"line":32,"column":1}},"key":"zCy60Qph6F"},{"type":"text","value":", ","position":{"start":{"line":32,"column":1},"end":{"line":32,"column":1}},"key":"zrjHHh3zYO"},{"type":"inlineCode","value":"test","position":{"start":{"line":32,"column":1},"end":{"line":32,"column":1}},"key":"O8o6qM6mLP"},{"type":"text","value":", ","position":{"start":{"line":32,"column":1},"end":{"line":32,"column":1}},"key":"XzCJpUSVPO"},{"type":"inlineCode","value":"check","position":{"start":{"line":32,"column":1},"end":{"line":32,"column":1}},"key":"tYrsmdJFUq"},{"type":"text","value":", ","position":{"start":{"line":32,"column":1},"end":{"line":32,"column":1}},"key":"CqWcusPDwP"},{"type":"inlineCode","value":"release","position":{"start":{"line":32,"column":1},"end":{"line":32,"column":1}},"key":"IahjmJuY5t"},{"type":"text","value":", ","position":{"start":{"line":32,"column":1},"end":{"line":32,"column":1}},"key":"SejImtzQPc"},{"type":"inlineCode","value":"ci","position":{"start":{"line":32,"column":1},"end":{"line":32,"column":1}},"key":"Wmdes7DE1O"},{"type":"text","value":").","position":{"start":{"line":32,"column":1},"end":{"line":32,"column":1}},"key":"Ph7fQCmYk2"}],"key":"p47HcBz4Vt"}],"key":"ZbZYE05WzW"},{"type":"listItem","spread":true,"position":{"start":{"line":33,"column":1},"end":{"line":33,"column":1}},"children":[{"type":"paragraph","children":[{"type":"text","value":"Selector-based precision (","position":{"start":{"line":33,"column":1},"end":{"line":33,"column":1}},"key":"lx4AJ55a2s"},{"type":"inlineCode","value":"test:unit","position":{"start":{"line":33,"column":1},"end":{"line":33,"column":1}},"key":"ulXfeA9yiN"},{"type":"text","value":", ","position":{"start":{"line":33,"column":1},"end":{"line":33,"column":1}},"key":"NZAA9nRyN2"},{"type":"inlineCode","value":"check:pr","position":{"start":{"line":33,"column":1},"end":{"line":33,"column":1}},"key":"xWmRCn6xvM"},{"type":"text","value":", ","position":{"start":{"line":33,"column":1},"end":{"line":33,"column":1}},"key":"mOcnZjOxoc"},{"type":"inlineCode","value":"ci:generate","position":{"start":{"line":33,"column":1},"end":{"line":33,"column":1}},"key":"zWa5eHjvTy"},{"type":"text","value":").","position":{"start":{"line":33,"column":1},"end":{"line":33,"column":1}},"key":"pB6Sj0hPGS"}],"key":"smkEzKBiHj"}],"key":"coFXGDPZmr"},{"type":"listItem","spread":true,"position":{"start":{"line":34,"column":1},"end":{"line":35,"column":1}},"children":[{"type":"paragraph","children":[{"type":"text","value":"Config-first policy (","position":{"start":{"line":34,"column":1},"end":{"line":34,"column":1}},"key":"CAeskdm6c3"},{"type":"inlineCode","value":"targets.*","position":{"start":{"line":34,"column":1},"end":{"line":34,"column":1}},"key":"KnOlNEJ6Q1"},{"type":"text","value":") with deterministic ","key":"xEOzg5NF8P"},{"type":"abbreviation","title":"Continuous Integration.","children":[{"type":"text","value":"CI","key":"OvoShqMQBN"}],"key":"BHEjOnukQf"},{"type":"text","value":" generation.","key":"KayHSDgxLF"}],"key":"rGLqhvJQIo"}],"key":"YuB9aG6ck6"}],"key":"ycmKU2A5YA"},{"type":"heading","depth":3,"position":{"start":{"line":36,"column":1},"end":{"line":36,"column":1}},"children":[{"type":"text","value":"Who It Is For","position":{"start":{"line":36,"column":1},"end":{"line":36,"column":1}},"key":"cdcAg0PWJp"}],"identifier":"who-it-is-for","label":"Who It Is For","html_id":"who-it-is-for","implicit":true,"key":"zWVXwiClbZ"},{"type":"list","ordered":false,"spread":false,"position":{"start":{"line":38,"column":1},"end":{"line":41,"column":1}},"children":[{"type":"listItem","spread":true,"position":{"start":{"line":38,"column":1},"end":{"line":38,"column":1}},"children":[{"type":"paragraph","children":[{"type":"text","value":"Teams maintaining one or many repositories with inconsistent local/","key":"Tdx3AqSfdD"},{"type":"abbreviation","title":"Continuous Integration.","children":[{"type":"text","value":"CI","key":"sJCNJbkFDk"}],"key":"vYQA2wXQr8"},{"type":"text","value":" workflows.","key":"LG3AYoOytA"}],"key":"YKaLcGP5YF"}],"key":"axPWBu40Gc"},{"type":"listItem","spread":true,"position":{"start":{"line":39,"column":1},"end":{"line":39,"column":1}},"children":[{"type":"paragraph","children":[{"type":"text","value":"Engineers who want predictable quality gates without custom per-repo script sprawl.","position":{"start":{"line":39,"column":1},"end":{"line":39,"column":1}},"key":"FYfC4QLauq"}],"key":"lGLciklrh9"}],"key":"HuroQ0lX7m"},{"type":"listItem","spread":true,"position":{"start":{"line":40,"column":1},"end":{"line":41,"column":1}},"children":[{"type":"paragraph","children":[{"type":"text","value":"Contributors extending workflow behavior through explicit extension capabilities.","position":{"start":{"line":40,"column":1},"end":{"line":40,"column":1}},"key":"HaJ16A0rIm"}],"key":"JnFq5FeYT4"}],"key":"sTbeuCq16e"}],"key":"tC4fvkeDHP"},{"type":"heading","depth":3,"position":{"start":{"line":42,"column":1},"end":{"line":42,"column":1}},"children":[{"type":"text","value":"Mission and Objectives","position":{"start":{"line":42,"column":1},"end":{"line":42,"column":1}},"key":"BCDiL0Ghz7"}],"identifier":"mission-and-objectives","label":"Mission and Objectives","html_id":"mission-and-objectives","implicit":true,"key":"ILsd6y1TUs"},{"type":"paragraph","position":{"start":{"line":44,"column":1},"end":{"line":44,"column":1}},"children":[{"type":"text","value":"Mission: make software delivery workflows consistent, repeatable, and easy to reason about.","position":{"start":{"line":44,"column":1},"end":{"line":44,"column":1}},"key":"avdMBvSuBG"}],"key":"vJTvDCV1DC"},{"type":"paragraph","position":{"start":{"line":46,"column":1},"end":{"line":46,"column":1}},"children":[{"type":"text","value":"Objectives:","position":{"start":{"line":46,"column":1},"end":{"line":46,"column":1}},"key":"ByxDTozoyg"}],"key":"eqgNt5c3OI"},{"type":"list","ordered":false,"spread":false,"position":{"start":{"line":48,"column":1},"end":{"line":52,"column":1}},"children":[{"type":"listItem","spread":true,"position":{"start":{"line":48,"column":1},"end":{"line":48,"column":1}},"children":[{"type":"paragraph","children":[{"type":"text","value":"define one canonical command surface across stacks","position":{"start":{"line":48,"column":1},"end":{"line":48,"column":1}},"key":"UvfxiqEujp"}],"key":"VrldyGtbmB"}],"key":"HVlkWhdWKo"},{"type":"listItem","spread":true,"position":{"start":{"line":49,"column":1},"end":{"line":49,"column":1}},"children":[{"type":"paragraph","children":[{"type":"text","value":"keep local and ","key":"U74dgkSTQ8"},{"type":"abbreviation","title":"Continuous Integration.","children":[{"type":"text","value":"CI","key":"KEtB9KV4dq"}],"key":"R3xnbhDmm0"},{"type":"text","value":" behavior aligned from the same config contract","key":"xma2SaaShT"}],"key":"IaQPr2IZhU"}],"key":"b1zez2hZmi"},{"type":"listItem","spread":true,"position":{"start":{"line":50,"column":1},"end":{"line":50,"column":1}},"children":[{"type":"paragraph","children":[{"type":"text","value":"make workflow policy explicit and versionable (","position":{"start":{"line":50,"column":1},"end":{"line":50,"column":1}},"key":"UR5XTwJfeL"},{"type":"inlineCode","value":"devflow.toml","position":{"start":{"line":50,"column":1},"end":{"line":50,"column":1}},"key":"aNR0MvIRIO"},{"type":"text","value":")","position":{"start":{"line":50,"column":1},"end":{"line":50,"column":1}},"key":"fXXu9tN6kX"}],"key":"fbXdV7Pp75"}],"key":"Q4Un4UbsQP"},{"type":"listItem","spread":true,"position":{"start":{"line":51,"column":1},"end":{"line":52,"column":1}},"children":[{"type":"paragraph","children":[{"type":"text","value":"enable safe extensibility through capability-checked extensions","position":{"start":{"line":51,"column":1},"end":{"line":51,"column":1}},"key":"CR49Y0dDXn"}],"key":"OKJ0BhEVrC"}],"key":"SIZmko6Zfg"}],"key":"hNzbTncoJh"},{"type":"heading","depth":3,"position":{"start":{"line":53,"column":1},"end":{"line":53,"column":1}},"children":[{"type":"text","value":"Documentation Paths","position":{"start":{"line":53,"column":1},"end":{"line":53,"column":1}},"key":"qrnyh4q5O7"}],"identifier":"documentation-paths","label":"Documentation Paths","html_id":"documentation-paths","implicit":true,"key":"Ok2P0rmhje"},{"type":"list","ordered":false,"spread":false,"position":{"start":{"line":55,"column":1},"end":{"line":56,"column":1}},"children":[{"type":"listItem","spread":true,"position":{"start":{"line":55,"column":1},"end":{"line":55,"column":1}},"children":[{"type":"paragraph","children":[{"type":"link","position":{"start":{"line":55,"column":1},"end":{"line":55,"column":1}},"children":[{"type":"text","value":"User Guide","position":{"start":{"line":55,"column":1},"end":{"line":55,"column":1}},"key":"ArKefgFmAV"}],"identifier":"devflow.user-guide.index","label":"devflow.user-guide.index","url":"/user-index","internal":true,"dataUrl":"/user-index.json","key":"YiKtdFI66I"},{"type":"text","value":": install, configure, and run Devflow.","position":{"start":{"line":55,"column":1},"end":{"line":55,"column":1}},"key":"QI2z5vSuYJ"}],"key":"QLf2jWqVOJ"}],"key":"O64MFwvxno"},{"type":"listItem","spread":true,"position":{"start":{"line":56,"column":1},"end":{"line":56,"column":1}},"children":[{"type":"paragraph","children":[{"type":"link","position":{"start":{"line":56,"column":1},"end":{"line":56,"column":1}},"children":[{"type":"text","value":"Developer Guide","position":{"start":{"line":56,"column":1},"end":{"line":56,"column":1}},"key":"hYmFbxDu8K"}],"identifier":"devflow.developer-guide.index","label":"devflow.developer-guide.index","url":"/developer-index","internal":true,"dataUrl":"/developer-index.json","key":"ZAyszC7Hsu"},{"type":"text","value":": architecture, extension model, and contribution workflow.","position":{"start":{"line":56,"column":1},"end":{"line":56,"column":1}},"key":"yMMO2CNbe9"}],"key":"PmsvwrVyHz"}],"key":"jZDBNH5Pbl"}],"key":"coWz7HC0ZH"}],"kind":"justified","key":"tLid83D7ns"}],"key":"PKNmvMHoOP"},"references":{"cite":{"order":[],"data":{}}},"footer":{"navigation":{"next":{"title":"User Guide","short_title":"User Guide","url":"/user-index","group":"Devflow"}}},"domain":"http://localhost:3000"}