{"version":3,"kind":"Article","sha256":"333a52aeb56863d4fa87a4dd2a870aaefd35c3ecdf90b64c2c2454a44df1f772","slug":"multi-stack","location":"/user-guide/multi-stack.md","dependencies":[],"frontmatter":{"title":"Multi-Stack Projects","label":"devflow.user-guide.multi-stack","content_includes_title":false,"authors":[{"nameParsed":{"literal":"Soft Mentor","given":"Soft","family":"Mentor"},"name":"Soft Mentor","id":"contributors-myst-generated-uid-0"}],"github":"https://github.com/softmentor/devflow","abbreviations":{"ADR":"Architecture Decision Record.","API":"Application Programming Interface.","CI":"Continuous Integration.","CLI":"Command Line Interface.","DAG":"Directed Acyclic Graph.","GHCR":"GitHub Container Registry.","PR":"Pull Request."},"numbering":{"title":{"offset":1}},"source_url":"https://github.com/softmentor/devflow/blob/main/docs/user-guide/multi-stack.md","edit_url":"https://github.com/softmentor/devflow/edit/main/docs/user-guide/multi-stack.md","exports":[{"format":"md","filename":"multi-stack.md","url":"/devflow/build/multi-stack-e02f1f98d5e5edd77edb168cda17d81a.md"}]},"mdast":{"type":"root","children":[{"type":"block","children":[{"type":"paragraph","position":{"start":{"line":8,"column":1},"end":{"line":8,"column":1}},"children":[{"type":"text","value":"Modern architectures often depend on multiple toolchains co-existing within the same repository (e.g., a ","position":{"start":{"line":8,"column":1},"end":{"line":8,"column":1}},"key":"V0M4OJkZWx"},{"type":"strong","position":{"start":{"line":8,"column":1},"end":{"line":8,"column":1}},"children":[{"type":"text","value":"Tauri","position":{"start":{"line":8,"column":1},"end":{"line":8,"column":1}},"key":"ZO3kKjNs6C"}],"key":"HJbD6rGgyf"},{"type":"text","value":" desktop app needing both ","position":{"start":{"line":8,"column":1},"end":{"line":8,"column":1}},"key":"s8jreaLzBY"},{"type":"inlineCode","value":"node","position":{"start":{"line":8,"column":1},"end":{"line":8,"column":1}},"key":"P7yCgPStHM"},{"type":"text","value":" for the frontend and ","position":{"start":{"line":8,"column":1},"end":{"line":8,"column":1}},"key":"PPvMFp7jNh"},{"type":"inlineCode","value":"rust","position":{"start":{"line":8,"column":1},"end":{"line":8,"column":1}},"key":"G5XvkLvDBY"},{"type":"text","value":" for the backend, or a full-stack monorepo).","position":{"start":{"line":8,"column":1},"end":{"line":8,"column":1}},"key":"yCceJUwLRm"}],"key":"x0Jpb864Vv"},{"type":"paragraph","position":{"start":{"line":10,"column":1},"end":{"line":10,"column":1}},"children":[{"type":"text","value":"Devflow’s container execution proxy seamlessly supports multiplexing extensions inside a single execution environment.","position":{"start":{"line":10,"column":1},"end":{"line":10,"column":1}},"key":"Y7j2eUEDWi"}],"key":"uyQHqBV5uP"},{"type":"heading","depth":2,"position":{"start":{"line":12,"column":1},"end":{"line":12,"column":1}},"children":[{"type":"text","value":"Configuring ","position":{"start":{"line":12,"column":1},"end":{"line":12,"column":1}},"key":"dBHCrG6Wgp"},{"type":"inlineCode","value":"devflow.toml","position":{"start":{"line":12,"column":1},"end":{"line":12,"column":1}},"key":"dYNXLNOH8M"}],"identifier":"configuring-devflow-toml","label":"Configuring devflow.toml","html_id":"configuring-devflow-toml","implicit":true,"key":"pNwmJkjbCM"},{"type":"paragraph","position":{"start":{"line":14,"column":1},"end":{"line":14,"column":1}},"children":[{"type":"text","value":"Instead of declaring a single stack, supply an array of requested stacks, and explicitly enable them in your ","position":{"start":{"line":14,"column":1},"end":{"line":14,"column":1}},"key":"oqJCjb8cXZ"},{"type":"inlineCode","value":"extensions","position":{"start":{"line":14,"column":1},"end":{"line":14,"column":1}},"key":"ySJIzyhXgZ"},{"type":"text","value":" block:","position":{"start":{"line":14,"column":1},"end":{"line":14,"column":1}},"key":"PVvu6qWndb"}],"key":"jAAe7o6K9p"},{"type":"code","lang":"toml","value":"[project]\nname = \"tauri-app\"\nstack = [\"rust\", \"node\"]\n\n[runtime]\nprofile = \"container\"\n\n[container]\nimage = \"tauri-ci\"\nengine = \"podman\"\n\n[targets]\npr = [\"fmt:check\", \"lint:static\", \"build:debug\", \"test:unit\"]\n\n[extensions.rust]\nsource = \"builtin\"\nrequired = true\n\n[extensions.node]\nsource = \"builtin\"\nrequired = true","position":{"start":{"line":16,"column":1},"end":{"line":38,"column":1}},"key":"NiMvB0pFKf"},{"type":"heading","depth":2,"position":{"start":{"line":40,"column":1},"end":{"line":40,"column":1}},"children":[{"type":"text","value":"The Multi-Stack Container Environment","position":{"start":{"line":40,"column":1},"end":{"line":40,"column":1}},"key":"gLlzs18XnQ"}],"identifier":"the-multi-stack-container-environment","label":"The Multi-Stack Container Environment","html_id":"the-multi-stack-container-environment","implicit":true,"key":"yZrA2eM4X9"},{"type":"paragraph","position":{"start":{"line":42,"column":1},"end":{"line":42,"column":1}},"children":[{"type":"text","value":"When generating your ","position":{"start":{"line":42,"column":1},"end":{"line":42,"column":1}},"key":"LPHqlwr2Cy"},{"type":"inlineCode","value":"Dockerfile.devflow","position":{"start":{"line":42,"column":1},"end":{"line":42,"column":1}},"key":"FOG2VJNZjk"},{"type":"text","value":", you must build a unified image containing ","position":{"start":{"line":42,"column":1},"end":{"line":42,"column":1}},"key":"F8MbBhkK9f"},{"type":"strong","position":{"start":{"line":42,"column":1},"end":{"line":42,"column":1}},"children":[{"type":"text","value":"all","position":{"start":{"line":42,"column":1},"end":{"line":42,"column":1}},"key":"nfewddJ29W"}],"key":"kMU11g5CdA"},{"type":"text","value":" requested toolchains.","position":{"start":{"line":42,"column":1},"end":{"line":42,"column":1}},"key":"ujxMLfSXJh"}],"key":"MzJGUGaF0w"},{"type":"paragraph","position":{"start":{"line":44,"column":1},"end":{"line":44,"column":1}},"children":[{"type":"text","value":"We recommend utilizing Multi-Stage Docker builds. Map standard ","position":{"start":{"line":44,"column":1},"end":{"line":44,"column":1}},"key":"jso1kShewL"},{"type":"inlineCode","value":"debian","position":{"start":{"line":44,"column":1},"end":{"line":44,"column":1}},"key":"SsedflNiCV"},{"type":"text","value":" dependencies in the base stage, and layer ","position":{"start":{"line":44,"column":1},"end":{"line":44,"column":1}},"key":"RVJgrIrxPc"},{"type":"inlineCode","value":"rustc","position":{"start":{"line":44,"column":1},"end":{"line":44,"column":1}},"key":"spyDPt1qbs"},{"type":"text","value":" and ","position":{"start":{"line":44,"column":1},"end":{"line":44,"column":1}},"key":"EqRnBaqsaQ"},{"type":"inlineCode","value":"node","position":{"start":{"line":44,"column":1},"end":{"line":44,"column":1}},"key":"BOEp0Wz2gm"},{"type":"text","value":" in the final ","position":{"start":{"line":44,"column":1},"end":{"line":44,"column":1}},"key":"fPZzmWWidC"},{"type":"inlineCode","value":"ci","position":{"start":{"line":44,"column":1},"end":{"line":44,"column":1}},"key":"XU5Vci7L8V"},{"type":"text","value":" stage. This avoids rebuilding large LLVM toolchains when only simple ","position":{"start":{"line":44,"column":1},"end":{"line":44,"column":1}},"key":"ZFkCyqAJGA"},{"type":"inlineCode","value":"package.json","position":{"start":{"line":44,"column":1},"end":{"line":44,"column":1}},"key":"yLkvYzn8D7"},{"type":"text","value":" updates occur.","position":{"start":{"line":44,"column":1},"end":{"line":44,"column":1}},"key":"E20AHjOq4d"}],"key":"BiVBW1FlES"},{"type":"heading","depth":3,"position":{"start":{"line":46,"column":1},"end":{"line":46,"column":1}},"children":[{"type":"text","value":"Example Multi-Stack Dockerfile (","position":{"start":{"line":46,"column":1},"end":{"line":46,"column":1}},"key":"rXns30dLAU"},{"type":"inlineCode","value":"tauri","position":{"start":{"line":46,"column":1},"end":{"line":46,"column":1}},"key":"LbynD5HZSU"},{"type":"text","value":")","position":{"start":{"line":46,"column":1},"end":{"line":46,"column":1}},"key":"KflcQRUGFE"}],"identifier":"example-multi-stack-dockerfile-tauri","label":"Example Multi-Stack Dockerfile (tauri)","html_id":"example-multi-stack-dockerfile-tauri","implicit":true,"key":"Zx8vdkdQnF"},{"type":"code","lang":"dockerfile","value":"FROM debian:12.8-slim AS base\n# ... install curl, git, build-essential ...\n\nFROM rust:1.93.1-slim-bookworm AS ci\nCOPY --from=base / /\n# Install Node alongside Rust\nRUN curl -fsSL https://deb.nodesource.com/setup_22.x | bash - && apt-get install -y nodejs","position":{"start":{"line":47,"column":1},"end":{"line":55,"column":1}},"key":"NnMmAc3EDj"},{"type":"admonition","position":{"start":{"line":57,"column":1},"end":{"line":58,"column":1}},"children":[{"type":"admonitionTitle","children":[{"type":"text","value":"Important","key":"qh19mCBMwY"}],"key":"KpWgjR8dmi"},{"type":"paragraph","position":{"start":{"line":57,"column":1},"end":{"line":58,"column":1}},"children":[{"type":"text","value":"Never use moving tags like ","position":{"start":{"line":57,"column":1},"end":{"line":57,"column":1}},"key":"eCSWuTpknv"},{"type":"inlineCode","value":":latest","position":{"start":{"line":57,"column":1},"end":{"line":57,"column":1}},"key":"JhiHXRM3cb"},{"type":"text","value":" or setup scripts pointing to moving URLs if strict caching is critical. Pinning explicitly to ","position":{"start":{"line":57,"column":1},"end":{"line":57,"column":1}},"key":"aAjBZnsIrV"},{"type":"inlineCode","value":"debian:12.8-slim","position":{"start":{"line":57,"column":1},"end":{"line":57,"column":1}},"key":"UMujQ3GW5a"},{"type":"text","value":" and downloading exact architecture binaries (e.g., ","position":{"start":{"line":57,"column":1},"end":{"line":57,"column":1}},"key":"YrrJo4lSXZ"},{"type":"inlineCode","value":"sccache-v0.8.1-aarch64","position":{"start":{"line":57,"column":1},"end":{"line":57,"column":1}},"key":"TgAXkhPntF"},{"type":"text","value":") will ensure deterministic image fingerprinting.","position":{"start":{"line":57,"column":1},"end":{"line":57,"column":1}},"key":"yULziS1Yiq"}],"key":"HIWD3yDvwK"}],"kind":"important","class":"simple","key":"uLAgjon41o"},{"type":"heading","depth":2,"position":{"start":{"line":60,"column":1},"end":{"line":60,"column":1}},"children":[{"type":"text","value":"Execution Multiplexing","position":{"start":{"line":60,"column":1},"end":{"line":60,"column":1}},"key":"hkfcHKxuSo"}],"identifier":"execution-multiplexing","label":"Execution Multiplexing","html_id":"execution-multiplexing","implicit":true,"key":"WJIUiZaUhN"},{"type":"paragraph","position":{"start":{"line":62,"column":1},"end":{"line":62,"column":1}},"children":[{"type":"text","value":"When Devflow parses ","position":{"start":{"line":62,"column":1},"end":{"line":62,"column":1}},"key":"UX31olgS1G"},{"type":"inlineCode","value":"stack = [\"rust\", \"node\"]","position":{"start":{"line":62,"column":1},"end":{"line":62,"column":1}},"key":"YrbwXXxunp"},{"type":"text","value":" under ","position":{"start":{"line":62,"column":1},"end":{"line":62,"column":1}},"key":"ibJBuQbzsv"},{"type":"inlineCode","value":"profile = \"container\"","position":{"start":{"line":62,"column":1},"end":{"line":62,"column":1}},"key":"FMOAXo1uVr"},{"type":"text","value":", it will dynamically iterate across ","position":{"start":{"line":62,"column":1},"end":{"line":62,"column":1}},"key":"J55TtedsuP"},{"type":"strong","position":{"start":{"line":62,"column":1},"end":{"line":62,"column":1}},"children":[{"type":"text","value":"both","position":{"start":{"line":62,"column":1},"end":{"line":62,"column":1}},"key":"LyaUje6Cdu"}],"key":"GhdKtorGpA"},{"type":"text","value":" extensions:","position":{"start":{"line":62,"column":1},"end":{"line":62,"column":1}},"key":"llOKt0Y7bb"}],"key":"dQTqTccPF6"},{"type":"list","ordered":true,"start":1,"spread":false,"position":{"start":{"line":64,"column":1},"end":{"line":68,"column":1}},"children":[{"type":"listItem","spread":true,"position":{"start":{"line":64,"column":1},"end":{"line":64,"column":1}},"children":[{"type":"paragraph","children":[{"type":"text","value":"Devflow queries the ","position":{"start":{"line":64,"column":1},"end":{"line":64,"column":1}},"key":"g6z0KT1qwM"},{"type":"inlineCode","value":"node","position":{"start":{"line":64,"column":1},"end":{"line":64,"column":1}},"key":"NK83AW4Wln"},{"type":"text","value":" extension and receives the ","position":{"start":{"line":64,"column":1},"end":{"line":64,"column":1}},"key":"QV99PZlwje"},{"type":"inlineCode","value":"~/.npm","position":{"start":{"line":64,"column":1},"end":{"line":64,"column":1}},"key":"UNHYJ2juoG"},{"type":"text","value":" volume mapping.","position":{"start":{"line":64,"column":1},"end":{"line":64,"column":1}},"key":"k7ADUpaT5z"}],"key":"iBFQc4EYWc"}],"key":"WXGU5SKB4I"},{"type":"listItem","spread":true,"position":{"start":{"line":65,"column":1},"end":{"line":65,"column":1}},"children":[{"type":"paragraph","children":[{"type":"text","value":"Devflow queries the ","position":{"start":{"line":65,"column":1},"end":{"line":65,"column":1}},"key":"MV6kWMgI0Q"},{"type":"inlineCode","value":"rust","position":{"start":{"line":65,"column":1},"end":{"line":65,"column":1}},"key":"b7XlT2iLCh"},{"type":"text","value":" extension and receives the ","position":{"start":{"line":65,"column":1},"end":{"line":65,"column":1}},"key":"YrPlgBfyZJ"},{"type":"inlineCode","value":".cargo","position":{"start":{"line":65,"column":1},"end":{"line":65,"column":1}},"key":"OhmRNRwoDn"},{"type":"text","value":" and ","position":{"start":{"line":65,"column":1},"end":{"line":65,"column":1}},"key":"mWGDF2L4RF"},{"type":"inlineCode","value":"sccache","position":{"start":{"line":65,"column":1},"end":{"line":65,"column":1}},"key":"Cybt1fBI1J"},{"type":"text","value":" mapping.","position":{"start":{"line":65,"column":1},"end":{"line":65,"column":1}},"key":"RfNMIaCAuz"}],"key":"Jo3a64o4MU"}],"key":"tqjjUz4Pre"},{"type":"listItem","spread":true,"position":{"start":{"line":66,"column":1},"end":{"line":68,"column":1}},"children":[{"type":"paragraph","children":[{"type":"text","value":"Devflow launches ","position":{"start":{"line":66,"column":1},"end":{"line":66,"column":1}},"key":"W2UJD9Vgnm"},{"type":"emphasis","position":{"start":{"line":66,"column":1},"end":{"line":66,"column":1}},"children":[{"type":"text","value":"one","position":{"start":{"line":66,"column":1},"end":{"line":66,"column":1}},"key":"klY0T0WRtj"}],"key":"ABlMHEXj80"},{"type":"text","value":" single proxy container merging all volumes:\n","position":{"start":{"line":66,"column":1},"end":{"line":66,"column":1}},"key":"TX5OU2KjqX"},{"type":"inlineCode","value":"podman run -v .cache/devflow/node/npm:/root/.npm -v .cache/devflow/rust/cargo:/usr/local/cargo ... tauri-ci","position":{"start":{"line":66,"column":1},"end":{"line":66,"column":1}},"key":"KkPQSPpttg"}],"key":"M1rcalk0Xo"}],"key":"It3yCuiPSI"}],"key":"r9T8LrivW9"},{"type":"paragraph","position":{"start":{"line":69,"column":1},"end":{"line":69,"column":1}},"children":[{"type":"text","value":"This enables a command like ","position":{"start":{"line":69,"column":1},"end":{"line":69,"column":1}},"key":"DMF6FW7rkU"},{"type":"inlineCode","value":"dwf check:pr","position":{"start":{"line":69,"column":1},"end":{"line":69,"column":1}},"key":"mnuzUfpEql"},{"type":"text","value":" to seamlessly execute Node linters and Rust static analysis inside the exact same container state.","position":{"start":{"line":69,"column":1},"end":{"line":69,"column":1}},"key":"rWKPXrzUhU"}],"key":"cryo9Mq1Ej"}],"key":"owUHxOBItr"}],"key":"QwxQMLbUzH"},"references":{"cite":{"order":[],"data":{}}},"footer":{"navigation":{"prev":{"title":"New Stacks (Kotlin Example)","url":"/new-stacks","group":"Devflow"},"next":{"title":"Using Custom Extensions","url":"/custom-extensions","group":"Devflow"}}},"domain":"http://localhost:3000"}